{"expansion":{"idExpansion":1391,"name":"2005 Player Cards","icon":124},"card":[{"idProduct":256803,"idMetaproduct":203285,"idGame":1,"countReprints":"3","name":{"1":{"idLanguage":1,"languageName":"English","productName":"Antoine Ruel"},"2":{"idLanguage":2,"languageName":"French","productName":"Antoine Ruel"},"3":{"idLanguage":3,"languageName":"German","productName":"Antoine Ruel"},"4":{"idLanguage":4,"languageName":"Spanish","productName":"Antoine Ruel"},"5":{"idLanguage":5,"languageName":"Italian","productName":"Antoine Ruel"}},"website":"\/Products\/Singles\/2005+Player+Cards\/Antoine+Ruel","image":".\/img\/cards\/2005_Player_Cards\/antoine_ruel.jpg","category":{"idCategory":1,"categoryName":"Magic Single"},"expansion":"2005 Player Cards","expIcon":124,"number":null,"rarity":"Special"},{"idProduct":256804,"idMetaproduct":206030,"idGame":1,"countReprints":"1","name":{"1":{"idLanguage":1,"languageName":"English","productName":"Anton Jonsson"},"2":{"idLanguage":2,"languageName":"French","productName":"Anton Jonsson"},"3":{"idLanguage":3,"languageName":"German","productName":"Anton Jonsson"},"4":{"idLanguage":4,"languageName":"Spanish","productName":"Anton Jonsson"},"5":{"idLanguage":5,"languageName":"Italian","productName":"Anton Jonsson"}},"website":"\/Products\/Singles\/2005+Player+Cards\/Anton+Jonsson","image":".\/img\/cards\/2005_Player_Cards\/anton_jonsson.jpg","category":{"idCategory":1,"categoryName":"Magic Single"},"expansion":"2005 Player Cards","expIcon":124,"number":null,"rarity":"Special"},{"idProduct":256805,"idMetaproduct":203267,"idGame":1,"countReprints":"2","name":{"1":{"idLanguage":1,"languageName":"English","productName":"Antonino De Rosa"},"2":{"idLanguage":2,"languageName":"French","productName":"Antonino De Rosa"},"3":{"idLanguage":3,"languageName":"German","productName":"Antonino De Rosa"},"4":{"idLanguage":4,"languageName":"Spanish","productName":"Antonino De Rosa"},"5":{"idLanguage":5,"languageName":"Italian","productName":"Antonino De Rosa"}},"website":"\/Products\/Singles\/2005+Player+Cards\/Antonino+De+Rosa","image":".\/img\/cards\/2005_Player_Cards\/antonino_de_rosa.jpg","category":{"idCategory":1,"categoryName":"Magic Single"},"expansion":"2005 Player Cards","expIcon":124,"number":null,"rarity":"Special"},{"idProduct":256806,"idMetaproduct":206031,"idGame":1,"countReprints":"2","name":{"1":{"idLanguage":1,"languageName":"English","productName":"Bob Maher"},"2":{"idLanguage":2,"languageName":"French","productName":"Bob Maher"},"3":{"idLanguage":3,"languageName":"German","productName":"Bob Maher"},"4":{"idLanguage":4,"languageName":"Spanish","productName":"Bob Maher"},"5":{"idLanguage":5,"languageName":"Italian","productName":"Bob Maher"}},"website":"\/Products\/Singles\/2005+Player+Cards\/Bob+Maher","image":".\/img\/cards\/2005_Player_Cards\/bob_maher.jpg","category":{"idCategory":1,"categoryName":"Magic Single"},"expansion":"2005 Player Cards","expIcon":124,"number":null,"rarity":"Special"},{"idProduct":256807,"idMetaproduct":206032,"idGame":1,"countReprints":"1","name":{"1":{"idLanguage":1,"languageName":"English","productName":"Brian Kibler"},"2":{"idLanguage":2,"languageName":"French","productName":"Brian Kibler"},"3":{"idLanguage":3,"languageName":"German","productName":"Brian Kibler"},"4":{"idLanguage":4,"languageName":"Spanish","productName":"Brian Kibler"},"5":{"idLanguage":5,"languageName":"Italian","productName":"Brian Kibler"}},"website":"\/Products\/Singles\/2005+Player+Cards\/Brian+Kibler","image":".\/img\/cards\/2005_Player_Cards\/brian_kibler.jpg","category":{"idCategory":1,"categoryName":"Magic Single"},"expansion":"2005 Player Cards","expIcon":124,"number":null,"rarity":"Special"},{"idProduct":256808,"idMetaproduct":206033,"idGame":1,"countReprints":"2","name":{"1":{"idLanguage":1,"languageName":"English","productName":"Dave Humpherys"},"2":{"idLanguage":2,"languageName":"French","productName":"Dave Humpherys"},"3":{"idLanguage":3,"languageName":"German","productName":"Dave Humpherys"},"4":{"idLanguage":4,"languageName":"Spanish","productName":"Dave Humpherys"},"5":{"idLanguage":5,"languageName":"Italian","productName":"Dave Humpherys"}},"website":"\/Products\/Singles\/2005+Player+Cards\/Dave+Humpherys","image":".\/img\/cards\/2005_Player_Cards\/dave_humpherys.jpg","category":{"idCategory":1,"categoryName":"Magic Single"},"expansion":"2005 Player Cards","expIcon":124,"number":null,"rarity":"Special"},{"idProduct":256809,"idMetaproduct":206034,"idGame":1,"countReprints":"1","name":{"1":{"idLanguage":1,"languageName":"English","productName":"Eugene Harvey"},"2":{"idLanguage":2,"languageName":"French","productName":"Eugene Harvey"},"3":{"idLanguage":3,"languageName":"German","productName":"Eugene Harvey"},"4":{"idLanguage":4,"languageName":"Spanish","productName":"Eugene Harvey"},"5":{"idLanguage":5,"languageName":"Italian","productName":"Eugene Harvey"}},"website":"\/Products\/Singles\/2005+Player+Cards\/Eugene+Harvey","image":".\/img\/cards\/2005_Player_Cards\/eugene_harvey.jpg","category":{"idCategory":1,"categoryName":"Magic Single"},"expansion":"2005 Player Cards","expIcon":124,"number":null,"rarity":"Special"},{"idProduct":256810,"idMetaproduct":203280,"idGame":1,"countReprints":"3","name":{"1":{"idLanguage":1,"languageName":"English","productName":"Gabriel Nassif"},"2":{"idLanguage":2,"languageName":"French","productName":"Gabriel Nassif"},"3":{"idLanguage":3,"languageName":"German","productName":"Gabriel Nassif"},"4":{"idLanguage":4,"languageName":"Spanish","productName":"Gabriel Nassif"},"5":{"idLanguage":5,"languageName":"Italian","productName":"Gabriel Nassif"}},"website":"\/Products\/Singles\/2005+Player+Cards\/Gabriel+Nassif","image":".\/img\/cards\/2005_Player_Cards\/gabriel_nassif.jpg","category":{"idCategory":1,"categoryName":"Magic Single"},"expansion":"2005 Player Cards","expIcon":124,"number":null,"rarity":"Special"},{"idProduct":256811,"idMetaproduct":206035,"idGame":1,"countReprints":"1","name":{"1":{"idLanguage":1,"languageName":"English","productName":"Itaru Ishida"},"2":{"idLanguage":2,"languageName":"French","productName":"Itaru Ishida"},"3":{"idLanguage":3,"languageName":"German","productName":"Itaru Ishida"},"4":{"idLanguage":4,"languageName":"Spanish","productName":"Itaru Ishida"},"5":{"idLanguage":5,"languageName":"Italian","productName":"Itaru Ishida"}},"website":"\/Products\/Singles\/2005+Player+Cards\/Itaru+Ishida","image":".\/img\/cards\/2005_Player_Cards\/itaru_ishida.jpg","category":{"idCategory":1,"categoryName":"Magic Single"},"expansion":"2005 Player Cards","expIcon":124,"number":null,"rarity":"Special"},{"idProduct":256812,"idMetaproduct":206036,"idGame":1,"countReprints":"1","name":{"1":{"idLanguage":1,"languageName":"English","productName":"Jeroen Remie"},"2":{"idLanguage":2,"languageName":"French","productName":"Jeroen Remie"},"3":{"idLanguage":3,"languageName":"German","productName":"Jeroen Remie"},"4":{"idLanguage":4,"languageName":"Spanish","productName":"Jeroen Remie"},"5":{"idLanguage":5,"languageName":"Italian","productName":"Jeroen Remie"}},"website":"\/Products\/Singles\/2005+Player+Cards\/Jeroen+Remie","image":".\/img\/cards\/2005_Player_Cards\/jeroen_remie.jpg","category":{"idCategory":1,"categoryName":"Magic Single"},"expansion":"2005 Player Cards","expIcon":124,"number":null,"rarity":"Special"},{"idProduct":256813,"idMetaproduct":206037,"idGame":1,"countReprints":"1","name":{"1":{"idLanguage":1,"languageName":"English","productName":"Jose Barbero"},"2":{"idLanguage":2,"languageName":"French","productName":"Jose Barbero"},"3":{"idLanguage":3,"languageName":"German","productName":"Jose Barbero"},"4":{"idLanguage":4,"languageName":"Spanish","productName":"Jose Barbero"},"5":{"idLanguage":5,"languageName":"Italian","productName":"Jose Barbero"}},"website":"\/Products\/Singles\/2005+Player+Cards\/Jose+Barbero","image":".\/img\/cards\/2005_Player_Cards\/jose_barbero.jpg","category":{"idCategory":1,"categoryName":"Magic Single"},"expansion":"2005 Player Cards","expIcon":124,"number":null,"rarity":"Special"},{"idProduct":256814,"idMetaproduct":203281,"idGame":1,"countReprints":"3","name":{"1":{"idLanguage":1,"languageName":"English","productName":"Julien Nuijten"},"2":{"idLanguage":2,"languageName":"French","productName":"Julien Nuijten"},"3":{"idLanguage":3,"languageName":"German","productName":"Julien Nuijten"},"4":{"idLanguage":4,"languageName":"Spanish","productName":"Julien Nuijten"},"5":{"idLanguage":5,"languageName":"Italian","productName":"Julien Nuijten"}},"website":"\/Products\/Singles\/2005+Player+Cards\/Julien+Nuijten","image":".\/img\/cards\/2005_Player_Cards\/julien_nuijten.jpg","category":{"idCategory":1,"categoryName":"Magic Single"},"expansion":"2005 Player Cards","expIcon":124,"number":null,"rarity":"Special"},{"idProduct":256815,"idMetaproduct":206038,"idGame":1,"countReprints":"1","name":{"1":{"idLanguage":1,"languageName":"English","productName":"Kai Budde"},"2":{"idLanguage":2,"languageName":"French","productName":"Kai Budde"},"3":{"idLanguage":3,"languageName":"German","productName":"Kai Budde"},"4":{"idLanguage":4,"languageName":"Spanish","productName":"Kai Budde"},"5":{"idLanguage":5,"languageName":"Italian","productName":"Kai Budde"}},"website":"\/Products\/Singles\/2005+Player+Cards\/Kai+Budde","image":".\/img\/cards\/2005_Player_Cards\/kai_budde.jpg","category":{"idCategory":1,"categoryName":"Magic Single"},"expansion":"2005 Player Cards","expIcon":124,"number":null,"rarity":"Special"},{"idProduct":256816,"idMetaproduct":206039,"idGame":1,"countReprints":"1","name":{"1":{"idLanguage":1,"languageName":"English","productName":"Kamiel Cornelissen"},"2":{"idLanguage":2,"languageName":"French","productName":"Kamiel Cornelissen"},"3":{"idLanguage":3,"languageName":"German","productName":"Kamiel Cornelissen"},"4":{"idLanguage":4,"languageName":"Spanish","productName":"Kamiel Cornelissen"},"5":{"idLanguage":5,"languageName":"Italian","productName":"Kamiel Cornelissen"}},"website":"\/Products\/Singles\/2005+Player+Cards\/Kamiel+Cornelissen","image":".\/img\/cards\/2005_Player_Cards\/kamiel_cornelissen.jpg","category":{"idCategory":1,"categoryName":"Magic Single"},"expansion":"2005 Player Cards","expIcon":124,"number":null,"rarity":"Special"},{"idProduct":256817,"idMetaproduct":206040,"idGame":1,"countReprints":"1","name":{"1":{"idLanguage":1,"languageName":"English","productName":"Masahiko Morita"},"2":{"idLanguage":2,"languageName":"French","productName":"Masahiko Morita"},"3":{"idLanguage":3,"languageName":"German","productName":"Masahiko Morita"},"4":{"idLanguage":4,"languageName":"Spanish","productName":"Masahiko Morita"},"5":{"idLanguage":5,"languageName":"Italian","productName":"Masahiko Morita"}},"website":"\/Products\/Singles\/2005+Player+Cards\/Masahiko+Morita","image":".\/img\/cards\/2005_Player_Cards\/masahiko_morita.jpg","category":{"idCategory":1,"categoryName":"Magic Single"},"expansion":"2005 Player Cards","expIcon":124,"number":null,"rarity":"Special"},{"idProduct":256818,"idMetaproduct":203282,"idGame":1,"countReprints":"2","name":{"1":{"idLanguage":1,"languageName":"English","productName":"Masashi Oiso"},"2":{"idLanguage":2,"languageName":"French","productName":"Masashi Oiso"},"3":{"idLanguage":3,"languageName":"German","productName":"Masashi Oiso"},"4":{"idLanguage":4,"languageName":"Spanish","productName":"Masashi Oiso"},"5":{"idLanguage":5,"languageName":"Italian","productName":"Masashi Oiso"}},"website":"\/Products\/Singles\/2005+Player+Cards\/Masashi+Oiso","image":".\/img\/cards\/2005_Player_Cards\/masashi_oiso.jpg","category":{"idCategory":1,"categoryName":"Magic Single"},"expansion":"2005 Player Cards","expIcon":124,"number":null,"rarity":"Special"},{"idProduct":256819,"idMetaproduct":206041,"idGame":1,"countReprints":"1","name":{"1":{"idLanguage":1,"languageName":"English","productName":"Masashiro Kuroda"},"2":{"idLanguage":2,"languageName":"French","productName":"Masashiro Kuroda"},"3":{"idLanguage":3,"languageName":"German","productName":"Masashiro Kuroda"},"4":{"idLanguage":4,"languageName":"Spanish","productName":"Masashiro Kuroda"},"5":{"idLanguage":5,"languageName":"Italian","productName":"Masashiro Kuroda"}},"website":"\/Products\/Singles\/2005+Player+Cards\/Masashiro+Kuroda","image":".\/img\/cards\/2005_Player_Cards\/masashiro_kuroda.jpg","category":{"idCategory":1,"categoryName":"Magic Single"},"expansion":"2005 Player Cards","expIcon":124,"number":null,"rarity":"Special"},{"idProduct":256820,"idMetaproduct":206042,"idGame":1,"countReprints":"1","name":{"1":{"idLanguage":1,"languageName":"English","productName":"Murray Evans"},"2":{"idLanguage":2,"languageName":"French","productName":"Murray Evans"},"3":{"idLanguage":3,"languageName":"German","productName":"Murray Evans"},"4":{"idLanguage":4,"languageName":"Spanish","productName":"Murray Evans"},"5":{"idLanguage":5,"languageName":"Italian","productName":"Murray Evans"}},"website":"\/Products\/Singles\/2005+Player+Cards\/Murray+Evans","image":".\/img\/cards\/2005_Player_Cards\/murray_evans.jpg","category":{"idCategory":1,"categoryName":"Magic Single"},"expansion":"2005 Player Cards","expIcon":124,"number":null,"rarity":"Special"},{"idProduct":256821,"idMetaproduct":203286,"idGame":1,"countReprints":"2","name":{"1":{"idLanguage":1,"languageName":"English","productName":"Olivier Ruel"},"2":{"idLanguage":2,"languageName":"French","productName":"Olivier Ruel"},"3":{"idLanguage":3,"languageName":"German","productName":"Olivier Ruel"},"4":{"idLanguage":4,"languageName":"Spanish","productName":"Olivier Ruel"},"5":{"idLanguage":5,"languageName":"Italian","productName":"Olivier Ruel"}},"website":"\/Products\/Singles\/2005+Player+Cards\/Olivier+Ruel","image":".\/img\/cards\/2005_Player_Cards\/olivier_ruel.jpg","category":{"idCategory":1,"categoryName":"Magic Single"},"expansion":"2005 Player Cards","expIcon":124,"number":null,"rarity":"Special"},{"idProduct":256822,"idMetaproduct":203277,"idGame":1,"countReprints":"3","name":{"1":{"idLanguage":1,"languageName":"English","productName":"Osyp Lebedowicz"},"2":{"idLanguage":2,"languageName":"French","productName":"Osyp Lebedowicz"},"3":{"idLanguage":3,"languageName":"German","productName":"Osyp Lebedowicz"},"4":{"idLanguage":4,"languageName":"Spanish","productName":"Osyp Lebedowicz"},"5":{"idLanguage":5,"languageName":"Italian","productName":"Osyp Lebedowicz"}},"website":"\/Products\/Singles\/2005+Player+Cards\/Osyp+Lebedowicz","image":".\/img\/cards\/2005_Player_Cards\/osyp_lebedowicz.jpg","category":{"idCategory":1,"categoryName":"Magic Single"},"expansion":"2005 Player Cards","expIcon":124,"number":null,"rarity":"Special"},{"idProduct":256823,"idMetaproduct":206043,"idGame":1,"countReprints":"1","name":{"1":{"idLanguage":1,"languageName":"English","productName":"Pierre Canali"},"2":{"idLanguage":2,"languageName":"French","productName":"Pierre Canali"},"3":{"idLanguage":3,"languageName":"German","productName":"Pierre Canali"},"4":{"idLanguage":4,"languageName":"Spanish","productName":"Pierre Canali"},"5":{"idLanguage":5,"languageName":"Italian","productName":"Pierre Canali"}},"website":"\/Products\/Singles\/2005+Player+Cards\/Pierre+Canali","image":".\/img\/cards\/2005_Player_Cards\/pierre_canali.jpg","category":{"idCategory":1,"categoryName":"Magic Single"},"expansion":"2005 Player Cards","expIcon":124,"number":null,"rarity":"Special"},{"idProduct":256824,"idMetaproduct":206044,"idGame":1,"countReprints":"2","name":{"1":{"idLanguage":1,"languageName":"English","productName":"Raphael Levy"},"2":{"idLanguage":2,"languageName":"French","productName":"Raphael Levy"},"3":{"idLanguage":3,"languageName":"German","productName":"Raphael Levy"},"4":{"idLanguage":4,"languageName":"Spanish","productName":"Raphael Levy"},"5":{"idLanguage":5,"languageName":"Italian","productName":"Raphael Levy"}},"website":"\/Products\/Singles\/2005+Player+Cards\/Raphael+Levy","image":".\/img\/cards\/2005_Player_Cards\/raphael_levy.jpg","category":{"idCategory":1,"categoryName":"Magic Single"},"expansion":"2005 Player Cards","expIcon":124,"number":null,"rarity":"Special"},{"idProduct":256825,"idMetaproduct":206045,"idGame":1,"countReprints":"1","name":{"1":{"idLanguage":1,"languageName":"English","productName":"Terry Soh"},"2":{"idLanguage":2,"languageName":"French","productName":"Terry Soh"},"3":{"idLanguage":3,"languageName":"German","productName":"Terry Soh"},"4":{"idLanguage":4,"languageName":"Spanish","productName":"Terry Soh"},"5":{"idLanguage":5,"languageName":"Italian","productName":"Terry Soh"}},"website":"\/Products\/Singles\/2005+Player+Cards\/Terry+Soh","image":".\/img\/cards\/2005_Player_Cards\/terry_soh.jpg","category":{"idCategory":1,"categoryName":"Magic Single"},"expansion":"2005 Player Cards","expIcon":124,"number":null,"rarity":"Special"},{"idProduct":256826,"idMetaproduct":206046,"idGame":1,"countReprints":"1","name":{"1":{"idLanguage":1,"languageName":"English","productName":"Tim Aten"},"2":{"idLanguage":2,"languageName":"French","productName":"Tim Aten"},"3":{"idLanguage":3,"languageName":"German","productName":"Tim Aten"},"4":{"idLanguage":4,"languageName":"Spanish","productName":"Tim Aten"},"5":{"idLanguage":5,"languageName":"Italian","productName":"Tim Aten"}},"website":"\/Products\/Singles\/2005+Player+Cards\/Tim+Aten","image":".\/img\/cards\/2005_Player_Cards\/tim_aten.jpg","category":{"idCategory":1,"categoryName":"Magic Single"},"expansion":"2005 Player Cards","expIcon":124,"number":null,"rarity":"Special"},{"idProduct":256827,"idMetaproduct":203269,"idGame":1,"countReprints":"2","name":{"1":{"idLanguage":1,"languageName":"English","productName":"Tsuyoshi Fujita"},"2":{"idLanguage":2,"languageName":"French","productName":"Tsuyoshi Fujita"},"3":{"idLanguage":3,"languageName":"German","productName":"Tsuyoshi Fujita"},"4":{"idLanguage":4,"languageName":"Spanish","productName":"Tsuyoshi Fujita"},"5":{"idLanguage":5,"languageName":"Italian","productName":"Tsuyoshi Fujita"}},"website":"\/Products\/Singles\/2005+Player+Cards\/Tsuyoshi+Fujita","image":".\/img\/cards\/2005_Player_Cards\/tsuyoshi_fujita.jpg","category":{"idCategory":1,"categoryName":"Magic Single"},"expansion":"2005 Player Cards","expIcon":124,"number":null,"rarity":"Special"}]}