{"expansion":{"idExpansion":1502,"name":"Tokens for MTG","icon":258},"card":[{"idProduct":269848,"idMetaproduct":200754,"idGame":1,"countReprints":"11","name":{"1":{"idLanguage":1,"languageName":"English","productName":"Wurm Token (Artifact 3\/3 Lifelink)"},"2":{"idLanguage":2,"languageName":"French","productName":"Wurm Token (Artifact 3\/3 Lifelink)"},"3":{"idLanguage":3,"languageName":"German","productName":"Wurm Token (Artifact 3\/3 Lifelink)"},"4":{"idLanguage":4,"languageName":"Spanish","productName":"Wurm Token (Artifact 3\/3 Lifelink)"},"5":{"idLanguage":5,"languageName":"Italian","productName":"Wurm Token (Artifact 3\/3 Lifelink)"}},"website":"\/Products\/Singles\/Tokens+for+MTG\/Wurm+Token+%28Artifact+3%2F3+Lifelink%29","image":".\/img\/cards\/Tokens_for_MTG\/wurm_token_artifact_33_lifelink.jpg","category":{"idCategory":1,"categoryName":"Magic Single"},"expansion":"Tokens for MTG","expIcon":258,"number":null,"rarity":"Token"},{"idProduct":269847,"idMetaproduct":200755,"idGame":1,"countReprints":"11","name":{"1":{"idLanguage":1,"languageName":"English","productName":"Wurm Token (Artifact 3\/3 Deathtouch)"},"2":{"idLanguage":2,"languageName":"French","productName":"Wurm Token (Artifact 3\/3 Deathtouch)"},"3":{"idLanguage":3,"languageName":"German","productName":"Wurm Token (Artifact 3\/3 Deathtouch)"},"4":{"idLanguage":4,"languageName":"Spanish","productName":"Wurm Token (Artifact 3\/3 Deathtouch)"},"5":{"idLanguage":5,"languageName":"Italian","productName":"Wurm Token (Artifact 3\/3 Deathtouch)"}},"website":"\/Products\/Singles\/Tokens+for+MTG\/Wurm+Token+%28Artifact+3%2F3+Deathtouch%29","image":".\/img\/cards\/Tokens_for_MTG\/wurm_token_artifact_33_deathtouch.jpg","category":{"idCategory":1,"categoryName":"Magic Single"},"expansion":"Tokens for MTG","expIcon":258,"number":null,"rarity":"Token"},{"idProduct":269846,"idMetaproduct":9102,"idGame":1,"countReprints":"55","name":{"1":{"idLanguage":1,"languageName":"English","productName":"Goblin Token (Red 1\/1) (Version 1)"},"2":{"idLanguage":2,"languageName":"French","productName":"Goblin Token (Red 1\/1) (Version 1)"},"3":{"idLanguage":3,"languageName":"German","productName":"Goblin Token (Red 1\/1) (Version 1)"},"4":{"idLanguage":4,"languageName":"Spanish","productName":"Goblin Token (Red 1\/1) (Version 1)"},"5":{"idLanguage":5,"languageName":"Italian","productName":"Goblin Token (Red 1\/1) (Version 1)"}},"website":"\/Products\/Singles\/Tokens+for+MTG\/Goblin+Token+%28Red+1%2F1%29+%28Version+1%29","image":".\/img\/cards\/Tokens_for_MTG\/goblin_token_red_111.jpg","category":{"idCategory":1,"categoryName":"Magic Single"},"expansion":"Tokens for MTG","expIcon":258,"number":null,"rarity":"Token"},{"idProduct":269845,"idMetaproduct":207817,"idGame":1,"countReprints":"3","name":{"1":{"idLanguage":1,"languageName":"English","productName":"Elf Token (Green 1\/1)"},"2":{"idLanguage":2,"languageName":"French","productName":"Elf Token (Green 1\/1)"},"3":{"idLanguage":3,"languageName":"German","productName":"Elf Token (Green 1\/1)"},"4":{"idLanguage":4,"languageName":"Spanish","productName":"Elf Token (Green 1\/1)"},"5":{"idLanguage":5,"languageName":"Italian","productName":"Elf Token (Green 1\/1)"}},"website":"\/Products\/Singles\/Tokens+for+MTG\/Elf+Token+%28Green+1%2F1%29","image":".\/img\/cards\/Tokens_for_MTG\/elf_token_green_11.jpg","category":{"idCategory":1,"categoryName":"Magic Single"},"expansion":"Tokens for MTG","expIcon":258,"number":null,"rarity":"Token"},{"idProduct":269844,"idMetaproduct":9843,"idGame":1,"countReprints":"24","name":{"1":{"idLanguage":1,"languageName":"English","productName":"Elemental Token (Red 1\/1)"},"2":{"idLanguage":2,"languageName":"French","productName":"Elemental Token (Red 1\/1)"},"3":{"idLanguage":3,"languageName":"German","productName":"Elemental Token (Red 1\/1)"},"4":{"idLanguage":4,"languageName":"Spanish","productName":"Elemental Token (Red 1\/1)"},"5":{"idLanguage":5,"languageName":"Italian","productName":"Elemental Token (Red 1\/1)"}},"website":"\/Products\/Singles\/Tokens+for+MTG\/Elemental+Token+%28Red+1%2F1%29","image":".\/img\/cards\/Tokens_for_MTG\/elemental_token_red_11.jpg","category":{"idCategory":1,"categoryName":"Magic Single"},"expansion":"Tokens for MTG","expIcon":258,"number":null,"rarity":"Token"},{"idProduct":282122,"idMetaproduct":9411,"idGame":1,"countReprints":"12","name":{"1":{"idLanguage":1,"languageName":"English","productName":"Sliver Token (Colorless 1\/1)"},"2":{"idLanguage":2,"languageName":"French","productName":"Sliver Token (Colorless 1\/1)"},"3":{"idLanguage":3,"languageName":"German","productName":"Sliver Token (Colorless 1\/1)"},"4":{"idLanguage":4,"languageName":"Spanish","productName":"Sliver Token (Colorless 1\/1)"},"5":{"idLanguage":5,"languageName":"Italian","productName":"Sliver Token (Colorless 1\/1)"}},"website":"\/Products\/Singles\/Tokens+for+MTG\/Sliver+Token+%28Colorless+1%2F1%29","image":".\/img\/cards\/Tokens_for_MTG\/sliver_token_colorless_11.jpg","category":{"idCategory":1,"categoryName":"Magic Single"},"expansion":"Tokens for MTG","expIcon":258,"number":null,"rarity":"Token"},{"idProduct":269401,"idMetaproduct":10804,"idGame":1,"countReprints":"52","name":{"1":{"idLanguage":1,"languageName":"English","productName":"Angel Token (White 4\/4)"},"2":{"idLanguage":2,"languageName":"French","productName":"Angel Token (White 4\/4)"},"3":{"idLanguage":3,"languageName":"German","productName":"Angel Token (White 4\/4)"},"4":{"idLanguage":4,"languageName":"Spanish","productName":"Angel Token (White 4\/4)"},"5":{"idLanguage":5,"languageName":"Italian","productName":"Angel Token (White 4\/4)"}},"website":"\/Products\/Singles\/Tokens+for+MTG\/Angel+Token+%28White+4%2F4%29","image":".\/img\/cards\/Tokens_for_MTG\/angel_token_white_44.jpg","category":{"idCategory":1,"categoryName":"Magic Single"},"expansion":"Tokens for MTG","expIcon":258,"number":null,"rarity":"Token"},{"idProduct":269402,"idMetaproduct":9400,"idGame":1,"countReprints":"34","name":{"1":{"idLanguage":1,"languageName":"English","productName":"Beast Token (Green 3\/3) (Version 1)"},"2":{"idLanguage":2,"languageName":"French","productName":"Beast Token (Green 3\/3) (Version 1)"},"3":{"idLanguage":3,"languageName":"German","productName":"Beast Token (Green 3\/3) (Version 1)"},"4":{"idLanguage":4,"languageName":"Spanish","productName":"Beast Token (Green 3\/3) (Version 1)"},"5":{"idLanguage":5,"languageName":"Italian","productName":"Beast Token (Green 3\/3) (Version 1)"}},"website":"\/Products\/Singles\/Tokens+for+MTG\/Beast+Token+%28Green+3%2F3%29+%28Version+1%29","image":".\/img\/cards\/Tokens_for_MTG\/beast_token_green_331.jpg","category":{"idCategory":1,"categoryName":"Magic Single"},"expansion":"Tokens for MTG","expIcon":258,"number":null,"rarity":"Token"},{"idProduct":269404,"idMetaproduct":9109,"idGame":1,"countReprints":"21","name":{"1":{"idLanguage":1,"languageName":"English","productName":"Dragon Token (Red 5\/5)"},"2":{"idLanguage":2,"languageName":"French","productName":"Dragon Token (Red 5\/5)"},"3":{"idLanguage":3,"languageName":"German","productName":"Dragon Token (Red 5\/5)"},"4":{"idLanguage":4,"languageName":"Spanish","productName":"Dragon Token (Red 5\/5)"},"5":{"idLanguage":5,"languageName":"Italian","productName":"Dragon Token (Red 5\/5)"}},"website":"\/Products\/Singles\/Tokens+for+MTG\/Dragon+Token+%28Red+5%2F5%29","image":".\/img\/cards\/Tokens_for_MTG\/dragon_token_red_55.jpg","category":{"idCategory":1,"categoryName":"Magic Single"},"expansion":"Tokens for MTG","expIcon":258,"number":null,"rarity":"Token"},{"idProduct":269406,"idMetaproduct":9105,"idGame":1,"countReprints":"53","name":{"1":{"idLanguage":1,"languageName":"English","productName":"Soldier Token (White 1\/1) (Version 1)"},"2":{"idLanguage":2,"languageName":"French","productName":"Soldier Token (White 1\/1) (Version 1)"},"3":{"idLanguage":3,"languageName":"German","productName":"Soldier Token (White 1\/1) (Version 1)"},"4":{"idLanguage":4,"languageName":"Spanish","productName":"Soldier Token (White 1\/1) (Version 1)"},"5":{"idLanguage":5,"languageName":"Italian","productName":"Soldier Token (White 1\/1) (Version 1)"}},"website":"\/Products\/Singles\/Tokens+for+MTG\/Soldier+Token+%28White+1%2F1%29+%28Version+1%29","image":".\/img\/cards\/Tokens_for_MTG\/soldier_token_white_111.jpg","category":{"idCategory":1,"categoryName":"Magic Single"},"expansion":"Tokens for MTG","expIcon":258,"number":null,"rarity":"Token"},{"idProduct":269403,"idMetaproduct":209423,"idGame":1,"countReprints":"9","name":{"1":{"idLanguage":1,"languageName":"English","productName":"Cat Soldier Token (White 1\/1)"},"2":{"idLanguage":2,"languageName":"French","productName":"Cat Soldier Token (White 1\/1)"},"3":{"idLanguage":3,"languageName":"German","productName":"Cat Soldier Token (White 1\/1)"},"4":{"idLanguage":4,"languageName":"Spanish","productName":"Cat Soldier Token (White 1\/1)"},"5":{"idLanguage":5,"languageName":"Italian","productName":"Cat Soldier Token (White 1\/1)"}},"website":"\/Products\/Singles\/Tokens+for+MTG\/Cat+Soldier+Token+%28White+1%2F1%29","image":".\/img\/cards\/Tokens_for_MTG\/cat_soldier_token_white_11.jpg","category":{"idCategory":1,"categoryName":"Magic Single"},"expansion":"Tokens for MTG","expIcon":258,"number":null,"rarity":"Token"},{"idProduct":269405,"idMetaproduct":9110,"idGame":1,"countReprints":"23","name":{"1":{"idLanguage":1,"languageName":"English","productName":"Saproling Token (Green 1\/1)"},"2":{"idLanguage":2,"languageName":"French","productName":"Saproling Token (Green 1\/1)"},"3":{"idLanguage":3,"languageName":"German","productName":"Saproling Token (Green 1\/1)"},"4":{"idLanguage":4,"languageName":"Spanish","productName":"Saproling Token (Green 1\/1)"},"5":{"idLanguage":5,"languageName":"Italian","productName":"Saproling Token (Green 1\/1)"}},"website":"\/Products\/Singles\/Tokens+for+MTG\/Saproling+Token+%28Green+1%2F1%29","image":".\/img\/cards\/Tokens_for_MTG\/saproling_token_green_11.jpg","category":{"idCategory":1,"categoryName":"Magic Single"},"expansion":"Tokens for MTG","expIcon":258,"number":null,"rarity":"Token"},{"idProduct":269407,"idMetaproduct":9847,"idGame":1,"countReprints":"47","name":{"1":{"idLanguage":1,"languageName":"English","productName":"Spirit Token (White 1\/1)"},"2":{"idLanguage":2,"languageName":"French","productName":"Spirit Token (White 1\/1)"},"3":{"idLanguage":3,"languageName":"German","productName":"Spirit Token (White 1\/1)"},"4":{"idLanguage":4,"languageName":"Spanish","productName":"Spirit Token (White 1\/1)"},"5":{"idLanguage":5,"languageName":"Italian","productName":"Spirit Token (White 1\/1)"}},"website":"\/Products\/Singles\/Tokens+for+MTG\/Spirit+Token+%28White+1%2F1%29","image":".\/img\/cards\/Tokens_for_MTG\/spirit_token_white_11.jpg","category":{"idCategory":1,"categoryName":"Magic Single"},"expansion":"Tokens for MTG","expIcon":258,"number":null,"rarity":"Token"},{"idProduct":269408,"idMetaproduct":9397,"idGame":1,"countReprints":"31","name":{"1":{"idLanguage":1,"languageName":"English","productName":"Wolf Token (Green 2\/2) (Version 1)"},"2":{"idLanguage":2,"languageName":"French","productName":"Wolf Token (Green 2\/2) (Version 1)"},"3":{"idLanguage":3,"languageName":"German","productName":"Wolf Token (Green 2\/2) (Version 1)"},"4":{"idLanguage":4,"languageName":"Spanish","productName":"Wolf Token (Green 2\/2) (Version 1)"},"5":{"idLanguage":5,"languageName":"Italian","productName":"Wolf Token (Green 2\/2) (Version 1)"}},"website":"\/Products\/Singles\/Tokens+for+MTG\/Wolf+Token+%28Green+2%2F2%29+%28Version+1%29","image":".\/img\/cards\/Tokens_for_MTG\/wolf_token_green_221.jpg","category":{"idCategory":1,"categoryName":"Magic Single"},"expansion":"Tokens for MTG","expIcon":258,"number":null,"rarity":"Token"},{"idProduct":269409,"idMetaproduct":9107,"idGame":1,"countReprints":"78","name":{"1":{"idLanguage":1,"languageName":"English","productName":"Zombie Token (Black 2\/2) (Version 1)"},"2":{"idLanguage":2,"languageName":"French","productName":"Zombie Token (Black 2\/2) (Version 1)"},"3":{"idLanguage":3,"languageName":"German","productName":"Zombie Token (Black 2\/2) (Version 1)"},"4":{"idLanguage":4,"languageName":"Spanish","productName":"Zombie Token (Black 2\/2) (Version 1)"},"5":{"idLanguage":5,"languageName":"Italian","productName":"Zombie Token (Black 2\/2) (Version 1)"}},"website":"\/Products\/Singles\/Tokens+for+MTG\/Zombie+Token+%28Black+2%2F2%29+%28Version+1%29","image":".\/img\/cards\/Tokens_for_MTG\/zombie_token_black_221.jpg","category":{"idCategory":1,"categoryName":"Magic Single"},"expansion":"Tokens for MTG","expIcon":258,"number":null,"rarity":"Token"},{"idProduct":272219,"idMetaproduct":210418,"idGame":1,"countReprints":"14","name":{"1":{"idLanguage":1,"languageName":"English","productName":"Warrior Token (White 1\/1) (Version 1)"},"2":{"idLanguage":2,"languageName":"French","productName":"Warrior Token (White 1\/1) (Version 1)"},"3":{"idLanguage":3,"languageName":"German","productName":"Warrior Token (White 1\/1) (Version 1)"},"4":{"idLanguage":4,"languageName":"Spanish","productName":"Warrior Token (White 1\/1) (Version 1)"},"5":{"idLanguage":5,"languageName":"Italian","productName":"Warrior Token (White 1\/1) (Version 1)"}},"website":"\/Products\/Singles\/Tokens+for+MTG\/Warrior+Token+%28White+1%2F1%29+%28Version+1%29","image":".\/img\/cards\/Tokens_for_MTG\/warrior_token_white_111.jpg","category":{"idCategory":1,"categoryName":"Magic Single"},"expansion":"Tokens for MTG","expIcon":258,"number":null,"rarity":"Token"},{"idProduct":272217,"idMetaproduct":210766,"idGame":1,"countReprints":"19","name":{"1":{"idLanguage":1,"languageName":"English","productName":"Monk Token (White 1\/1 Prowess)"},"2":{"idLanguage":2,"languageName":"French","productName":"Jeton de Moine (1\/1 Blanc Prouesse)"},"3":{"idLanguage":3,"languageName":"German","productName":"M\u00f6nch-Spielstein (Weiss 1\/1 Bravour)"},"4":{"idLanguage":4,"languageName":"Spanish","productName":"Ficha de Monje (1\/1 Blanco Destreza)"},"5":{"idLanguage":5,"languageName":"Italian","productName":"Pedina Monaco (1\/1 Bianca Prodezza)"}},"website":"\/Products\/Singles\/Tokens+for+MTG\/Monk+Token+%28White+1%2F1+Prowess%29","image":".\/img\/cards\/Tokens_for_MTG\/monk_token_white_11_prowess.jpg","category":{"idCategory":1,"categoryName":"Magic Single"},"expansion":"Tokens for MTG","expIcon":258,"number":null,"rarity":"Token"},{"idProduct":272221,"idMetaproduct":9105,"idGame":1,"countReprints":"53","name":{"1":{"idLanguage":1,"languageName":"English","productName":"Soldier Token (White 1\/1) (Version 2)"},"2":{"idLanguage":2,"languageName":"French","productName":"Soldier Token (White 1\/1) (Version 2)"},"3":{"idLanguage":3,"languageName":"German","productName":"Soldier Token (White 1\/1) (Version 2)"},"4":{"idLanguage":4,"languageName":"Spanish","productName":"Soldier Token (White 1\/1) (Version 2)"},"5":{"idLanguage":5,"languageName":"Italian","productName":"Soldier Token (White 1\/1) (Version 2)"}},"website":"\/Products\/Singles\/Tokens+for+MTG\/Soldier+Token+%28White+1%2F1%29+%28Version+2%29","image":".\/img\/cards\/Tokens_for_MTG\/soldier_token_white_112.jpg","category":{"idCategory":1,"categoryName":"Magic Single"},"expansion":"Tokens for MTG","expIcon":258,"number":null,"rarity":"Token"},{"idProduct":272218,"idMetaproduct":207818,"idGame":1,"countReprints":"3","name":{"1":{"idLanguage":1,"languageName":"English","productName":"Faerie Token (Black 1\/1) (Version 1)"},"2":{"idLanguage":2,"languageName":"French","productName":"Faerie Token (Black 1\/1) (Version 1)"},"3":{"idLanguage":3,"languageName":"German","productName":"Faerie Token (Black 1\/1) (Version 1)"},"4":{"idLanguage":4,"languageName":"Spanish","productName":"Faerie Token (Black 1\/1) (Version 1)"},"5":{"idLanguage":5,"languageName":"Italian","productName":"Faerie Token (Black 1\/1) (Version 1)"}},"website":"\/Products\/Singles\/Tokens+for+MTG\/Faerie+Token+%28Black+1%2F1%29+%28Version+1%29","image":".\/img\/cards\/Tokens_for_MTG\/faerie_token_black_111.jpg","category":{"idCategory":1,"categoryName":"Magic Single"},"expansion":"Tokens for MTG","expIcon":258,"number":null,"rarity":"Token"},{"idProduct":271353,"idMetaproduct":210682,"idGame":1,"countReprints":"1","name":{"1":{"idLanguage":1,"languageName":"English","productName":"Bird Token (White 3\/4)"},"2":{"idLanguage":2,"languageName":"French","productName":"Bird Token (White 3\/4)"},"3":{"idLanguage":3,"languageName":"German","productName":"Bird Token (White 3\/4)"},"4":{"idLanguage":4,"languageName":"Spanish","productName":"Bird Token (White 3\/4)"},"5":{"idLanguage":5,"languageName":"Italian","productName":"Bird Token (White 3\/4)"}},"website":"\/Products\/Singles\/Tokens+for+MTG\/Bird+Token+%28White+3%2F4%29","image":".\/img\/cards\/Tokens_for_MTG\/bird_token_white_34.jpg","category":{"idCategory":1,"categoryName":"Magic Single"},"expansion":"Tokens for MTG","expIcon":258,"number":null,"rarity":"Token"},{"idProduct":272220,"idMetaproduct":9106,"idGame":1,"countReprints":"15","name":{"1":{"idLanguage":1,"languageName":"English","productName":"Squirrel Token (Green 1\/1)"},"2":{"idLanguage":2,"languageName":"French","productName":"Squirrel Token (Green 1\/1)"},"3":{"idLanguage":3,"languageName":"German","productName":"Squirrel Token (Green 1\/1)"},"4":{"idLanguage":4,"languageName":"Spanish","productName":"Squirrel Token (Green 1\/1)"},"5":{"idLanguage":5,"languageName":"Italian","productName":"Squirrel Token (Green 1\/1)"}},"website":"\/Products\/Singles\/Tokens+for+MTG\/Squirrel+Token+%28Green+1%2F1%29","image":".\/img\/cards\/Tokens_for_MTG\/squirrel_token_green_11.jpg","category":{"idCategory":1,"categoryName":"Magic Single"},"expansion":"Tokens for MTG","expIcon":258,"number":null,"rarity":"Token"},{"idProduct":271354,"idMetaproduct":207998,"idGame":1,"countReprints":"15","name":{"1":{"idLanguage":1,"languageName":"English","productName":"Elemental Token (Green and White *\/*)"},"2":{"idLanguage":2,"languageName":"French","productName":"Elemental Token (Green and White *\/*)"},"3":{"idLanguage":3,"languageName":"German","productName":"Elemental Token (Green and White *\/*)"},"4":{"idLanguage":4,"languageName":"Spanish","productName":"Elemental Token (Green and White *\/*)"},"5":{"idLanguage":5,"languageName":"Italian","productName":"Elemental Token (Green and White *\/*)"}},"website":"\/Products\/Singles\/Tokens+for+MTG\/Elemental+Token+%28Green+and+White+%2A%2F%2A%29","image":".\/img\/cards\/Tokens_for_MTG\/elemental_token_green_and_white_xx.jpg","category":{"idCategory":1,"categoryName":"Magic Single"},"expansion":"Tokens for MTG","expIcon":258,"number":null,"rarity":"Token"},{"idProduct":271355,"idMetaproduct":202349,"idGame":1,"countReprints":"14","name":{"1":{"idLanguage":1,"languageName":"English","productName":"Germ Token (Black 0\/0)"},"2":{"idLanguage":2,"languageName":"French","productName":"Germ Token (Black 0\/0)"},"3":{"idLanguage":3,"languageName":"German","productName":"Germ Token (Black 0\/0)"},"4":{"idLanguage":4,"languageName":"Spanish","productName":"Germ Token (Black 0\/0)"},"5":{"idLanguage":5,"languageName":"Italian","productName":"Germ Token (Black 0\/0)"}},"website":"\/Products\/Singles\/Tokens+for+MTG\/Germ+Token+%28Black+0%2F0%29","image":".\/img\/cards\/Tokens_for_MTG\/germ_token_black_00.jpg","category":{"idCategory":1,"categoryName":"Magic Single"},"expansion":"Tokens for MTG","expIcon":258,"number":null,"rarity":"Token"},{"idProduct":271356,"idMetaproduct":210169,"idGame":1,"countReprints":"6","name":{"1":{"idLanguage":1,"languageName":"English","productName":"Insect Token (Green 1\/1 Flying, Deathtouch)"},"2":{"idLanguage":2,"languageName":"French","productName":"Insect Token (Green 1\/1 Flying, Deathtouch)"},"3":{"idLanguage":3,"languageName":"German","productName":"Insect Token (Green 1\/1 Flying, Deathtouch)"},"4":{"idLanguage":4,"languageName":"Spanish","productName":"Insect Token (Green 1\/1 Flying, Deathtouch)"},"5":{"idLanguage":5,"languageName":"Italian","productName":"Insect Token (Green 1\/1 Flying, Deathtouch)"}},"website":"\/Products\/Singles\/Tokens+for+MTG\/Insect+Token+%28Green+1%2F1+Flying%2C+Deathtouch%29","image":".\/img\/cards\/Tokens_for_MTG\/insect_token_green_11_flying_deathtouch.jpg","category":{"idCategory":1,"categoryName":"Magic Single"},"expansion":"Tokens for MTG","expIcon":258,"number":null,"rarity":"Token"},{"idProduct":271357,"idMetaproduct":210683,"idGame":1,"countReprints":"3","name":{"1":{"idLanguage":1,"languageName":"English","productName":"Kobold Token (Red 0\/1)"},"2":{"idLanguage":2,"languageName":"French","productName":"Kobold Token (Red 0\/1)"},"3":{"idLanguage":3,"languageName":"German","productName":"Kobold Token (Red 0\/1)"},"4":{"idLanguage":4,"languageName":"Spanish","productName":"Kobold Token (Red 0\/1)"},"5":{"idLanguage":5,"languageName":"Italian","productName":"Kobold Token (Red 0\/1)"}},"website":"\/Products\/Singles\/Tokens+for+MTG\/Kobold+Token+%28Red+0%2F1%29","image":".\/img\/cards\/Tokens_for_MTG\/kobold_token_red_01.jpg","category":{"idCategory":1,"categoryName":"Magic Single"},"expansion":"Tokens for MTG","expIcon":258,"number":null,"rarity":"Token"},{"idProduct":271358,"idMetaproduct":208832,"idGame":1,"countReprints":"6","name":{"1":{"idLanguage":1,"languageName":"English","productName":"Satyr Token (Red and Green 2\/2)"},"2":{"idLanguage":2,"languageName":"French","productName":"Satyr Token (Red and Green 2\/2)"},"3":{"idLanguage":3,"languageName":"German","productName":"Satyr Token (Red and Green 2\/2)"},"4":{"idLanguage":4,"languageName":"Spanish","productName":"Satyr Token (Red and Green 2\/2)"},"5":{"idLanguage":5,"languageName":"Italian","productName":"Satyr Token (Red and Green 2\/2)"}},"website":"\/Products\/Singles\/Tokens+for+MTG\/Satyr+Token+%28Red+and+Green+2%2F2%29","image":".\/img\/cards\/Tokens_for_MTG\/satyr_token_red_and_green_22.jpg","category":{"idCategory":1,"categoryName":"Magic Single"},"expansion":"Tokens for MTG","expIcon":258,"number":null,"rarity":"Token"},{"idProduct":271359,"idMetaproduct":204200,"idGame":1,"countReprints":"20","name":{"1":{"idLanguage":1,"languageName":"English","productName":"Vampire Token (Black 2\/2)"},"2":{"idLanguage":2,"languageName":"French","productName":"Vampire Token (Black 2\/2)"},"3":{"idLanguage":3,"languageName":"German","productName":"Vampire Token (Black 2\/2)"},"4":{"idLanguage":4,"languageName":"Spanish","productName":"Vampire Token (Black 2\/2)"},"5":{"idLanguage":5,"languageName":"Italian","productName":"Vampire Token (Black 2\/2)"}},"website":"\/Products\/Singles\/Tokens+for+MTG\/Vampire+Token+%28Black+2%2F2%29","image":".\/img\/cards\/Tokens_for_MTG\/vampire_token_black_22.jpg","category":{"idCategory":1,"categoryName":"Magic Single"},"expansion":"Tokens for MTG","expIcon":258,"number":null,"rarity":"Token"},{"idProduct":273044,"idMetaproduct":9846,"idGame":1,"countReprints":"7","name":{"1":{"idLanguage":1,"languageName":"English","productName":"Rat Token (Black 1\/1)"},"2":{"idLanguage":2,"languageName":"French","productName":"Rat Token (Black 1\/1)"},"3":{"idLanguage":3,"languageName":"German","productName":"Rat Token (Black 1\/1)"},"4":{"idLanguage":4,"languageName":"Spanish","productName":"Rat Token (Black 1\/1)"},"5":{"idLanguage":5,"languageName":"Italian","productName":"Rat Token (Black 1\/1)"}},"website":"\/Products\/Singles\/Tokens+for+MTG\/Rat+Token+%28Black+1%2F1%29","image":".\/img\/cards\/Tokens_for_MTG\/rat_token_black_11.jpg","category":{"idCategory":1,"categoryName":"Magic Single"},"expansion":"Tokens for MTG","expIcon":258,"number":null,"rarity":"Token"},{"idProduct":282123,"idMetaproduct":10268,"idGame":1,"countReprints":"10","name":{"1":{"idLanguage":1,"languageName":"English","productName":"Dragon Token (Red 4\/4)"},"2":{"idLanguage":2,"languageName":"French","productName":"Dragon Token (Red 4\/4)"},"3":{"idLanguage":3,"languageName":"German","productName":"Dragon Token (Red 4\/4)"},"4":{"idLanguage":4,"languageName":"Spanish","productName":"Dragon Token (Red 4\/4)"},"5":{"idLanguage":5,"languageName":"Italian","productName":"Dragon Token (Red 4\/4)"}},"website":"\/Products\/Singles\/Tokens+for+MTG\/Dragon+Token+%28Red+4%2F4%29","image":".\/img\/cards\/Tokens_for_MTG\/dragon_token_red_44.jpg","category":{"idCategory":1,"categoryName":"Magic Single"},"expansion":"Tokens for MTG","expIcon":258,"number":null,"rarity":"Token"},{"idProduct":271360,"idMetaproduct":210426,"idGame":1,"countReprints":"3","name":{"1":{"idLanguage":1,"languageName":"English","productName":"Voja Wolf Token (Green and White 2\/2)"},"2":{"idLanguage":2,"languageName":"French","productName":"Voja Wolf Token (Green and White 2\/2)"},"3":{"idLanguage":3,"languageName":"German","productName":"Voja Wolf Token (Green and White 2\/2)"},"4":{"idLanguage":4,"languageName":"Spanish","productName":"Voja Wolf Token (Green and White 2\/2)"},"5":{"idLanguage":5,"languageName":"Italian","productName":"Voja Wolf Token (Green and White 2\/2)"}},"website":"\/Products\/Singles\/Tokens+for+MTG\/Voja+Wolf+Token+%28Green+and+White+2%2F2%29","image":".\/img\/cards\/Tokens_for_MTG\/voja_wolf_token_green_and_white_22.jpg","category":{"idCategory":1,"categoryName":"Magic Single"},"expansion":"Tokens for MTG","expIcon":258,"number":null,"rarity":"Token"},{"idProduct":282124,"idMetaproduct":210707,"idGame":1,"countReprints":"3","name":{"1":{"idLanguage":1,"languageName":"English","productName":"Manifest Token"},"2":{"idLanguage":2,"languageName":"French","productName":"Manifest Token"},"3":{"idLanguage":3,"languageName":"German","productName":"Manifest Token"},"4":{"idLanguage":4,"languageName":"Spanish","productName":"Manifest Token"},"5":{"idLanguage":5,"languageName":"Italian","productName":"Manifest Token"}},"website":"\/Products\/Singles\/Tokens+for+MTG\/Manifest+Token","image":".\/img\/cards\/Tokens_for_MTG\/manifest_token.jpg","category":{"idCategory":1,"categoryName":"Magic Single"},"expansion":"Tokens for MTG","expIcon":258,"number":null,"rarity":"Token"},{"idProduct":282125,"idMetaproduct":9397,"idGame":1,"countReprints":"31","name":{"1":{"idLanguage":1,"languageName":"English","productName":"Wolf Token (Green 2\/2) (Version 2)"},"2":{"idLanguage":2,"languageName":"French","productName":"Wolf Token (Green 2\/2) (Version 2)"},"3":{"idLanguage":3,"languageName":"German","productName":"Wolf Token (Green 2\/2) (Version 2)"},"4":{"idLanguage":4,"languageName":"Spanish","productName":"Wolf Token (Green 2\/2) (Version 2)"},"5":{"idLanguage":5,"languageName":"Italian","productName":"Wolf Token (Green 2\/2) (Version 2)"}},"website":"\/Products\/Singles\/Tokens+for+MTG\/Wolf+Token+%28Green+2%2F2%29+%28Version+2%29","image":".\/img\/cards\/Tokens_for_MTG\/wolf_token_green_222.jpg","category":{"idCategory":1,"categoryName":"Magic Single"},"expansion":"Tokens for MTG","expIcon":258,"number":null,"rarity":"Token"},{"idProduct":282126,"idMetaproduct":10031,"idGame":1,"countReprints":"8","name":{"1":{"idLanguage":1,"languageName":"English","productName":"Goat Token (White 0\/1)"},"2":{"idLanguage":2,"languageName":"French","productName":"Goat Token (White 0\/1)"},"3":{"idLanguage":3,"languageName":"German","productName":"Goat Token (White 0\/1)"},"4":{"idLanguage":4,"languageName":"Spanish","productName":"Goat Token (White 0\/1)"},"5":{"idLanguage":5,"languageName":"Italian","productName":"Goat Token (White 0\/1)"}},"website":"\/Products\/Singles\/Tokens+for+MTG\/Goat+Token+%28White+0%2F1%29","image":".\/img\/cards\/Tokens_for_MTG\/goat_token_white_01.jpg","category":{"idCategory":1,"categoryName":"Magic Single"},"expansion":"Tokens for MTG","expIcon":258,"number":null,"rarity":"Token"},{"idProduct":283088,"idMetaproduct":200753,"idGame":1,"countReprints":"12","name":{"1":{"idLanguage":1,"languageName":"English","productName":"Golem Token (Artifact 3\/3)"},"2":{"idLanguage":2,"languageName":"French","productName":"Golem Token (Artifact 3\/3)"},"3":{"idLanguage":3,"languageName":"German","productName":"Golem Token (Artifact 3\/3)"},"4":{"idLanguage":4,"languageName":"Spanish","productName":"Golem Token (Artifact 3\/3)"},"5":{"idLanguage":5,"languageName":"Italian","productName":"Golem Token (Artifact 3\/3)"}},"website":"\/Products\/Singles\/Tokens+for+MTG\/Golem+Token+%28Artifact+3%2F3%29","image":".\/img\/cards\/Tokens_for_MTG\/golem_token_artifact_33.jpg","category":{"idCategory":1,"categoryName":"Magic Single"},"expansion":"Tokens for MTG","expIcon":258,"number":null,"rarity":"Token"},{"idProduct":283666,"idMetaproduct":206022,"idGame":1,"countReprints":"7","name":{"1":{"idLanguage":1,"languageName":"English","productName":"Drake Token (Blue 2\/2)"},"2":{"idLanguage":2,"languageName":"French","productName":"Drake Token (Blue 2\/2)"},"3":{"idLanguage":3,"languageName":"German","productName":"Drake Token (Blue 2\/2)"},"4":{"idLanguage":4,"languageName":"Spanish","productName":"Drake Token (Blue 2\/2)"},"5":{"idLanguage":5,"languageName":"Italian","productName":"Drake Token (Blue 2\/2)"}},"website":"\/Products\/Singles\/Tokens+for+MTG\/Drake+Token+%28Blue+2%2F2%29","image":".\/img\/cards\/Tokens_for_MTG\/drake_token_blue_22.jpg","category":{"idCategory":1,"categoryName":"Magic Single"},"expansion":"Tokens for MTG","expIcon":258,"number":null,"rarity":"Token"},{"idProduct":283667,"idMetaproduct":11137,"idGame":1,"countReprints":"12","name":{"1":{"idLanguage":1,"languageName":"English","productName":"Eldrazi Spawn Token (Colorless 0\/1)"},"2":{"idLanguage":2,"languageName":"French","productName":"Eldrazi Spawn Token (Colorless 0\/1)"},"3":{"idLanguage":3,"languageName":"German","productName":"Eldrazi Spawn Token (Colorless 0\/1)"},"4":{"idLanguage":4,"languageName":"Spanish","productName":"Eldrazi Spawn Token (Colorless 0\/1)"},"5":{"idLanguage":5,"languageName":"Italian","productName":"Eldrazi Spawn Token (Colorless 0\/1)"}},"website":"\/Products\/Singles\/Tokens+for+MTG\/Eldrazi+Spawn+Token+%28Colorless+0%2F1%29","image":".\/img\/cards\/Tokens_for_MTG\/eldrazi_spawn_token_colorless_01.jpg","category":{"idCategory":1,"categoryName":"Magic Single"},"expansion":"Tokens for MTG","expIcon":258,"number":null,"rarity":"Token"},{"idProduct":283670,"idMetaproduct":9847,"idGame":1,"countReprints":"47","name":{"1":{"idLanguage":1,"languageName":"English","productName":"Spirit Token (White 1\/1) (Version 2)"},"2":{"idLanguage":2,"languageName":"French","productName":"Spirit Token (White 1\/1) (Version 2)"},"3":{"idLanguage":3,"languageName":"German","productName":"Spirit Token (White 1\/1) (Version 2)"},"4":{"idLanguage":4,"languageName":"Spanish","productName":"Spirit Token (White 1\/1) (Version 2)"},"5":{"idLanguage":5,"languageName":"Italian","productName":"Spirit Token (White 1\/1) (Version 2)"}},"website":"\/Products\/Singles\/Tokens+for+MTG\/Spirit+Token+%28White+1%2F1%29+%28Version+2%29","image":".\/img\/cards\/Tokens_for_MTG\/spirit_token_white_112.jpg","category":{"idCategory":1,"categoryName":"Magic Single"},"expansion":"Tokens for MTG","expIcon":258,"number":null,"rarity":"Token"},{"idProduct":283671,"idMetaproduct":9107,"idGame":1,"countReprints":"78","name":{"1":{"idLanguage":1,"languageName":"English","productName":"Zombie Token (Black 2\/2) (Version 2)"},"2":{"idLanguage":2,"languageName":"French","productName":"Zombie Token (Black 2\/2) (Version 2)"},"3":{"idLanguage":3,"languageName":"German","productName":"Zombie Token (Black 2\/2) (Version 2)"},"4":{"idLanguage":4,"languageName":"Spanish","productName":"Zombie Token (Black 2\/2) (Version 2)"},"5":{"idLanguage":5,"languageName":"Italian","productName":"Zombie Token (Black 2\/2) (Version 2)"}},"website":"\/Products\/Singles\/Tokens+for+MTG\/Zombie+Token+%28Black+2%2F2%29+%28Version+2%29","image":".\/img\/cards\/Tokens_for_MTG\/zombie_token_black_222.jpg","category":{"idCategory":1,"categoryName":"Magic Single"},"expansion":"Tokens for MTG","expIcon":258,"number":null,"rarity":"Token"},{"idProduct":283720,"idMetaproduct":9105,"idGame":1,"countReprints":"53","name":{"1":{"idLanguage":1,"languageName":"English","productName":"Soldier Token (White 1\/1) (Version 3)"},"2":{"idLanguage":2,"languageName":"French","productName":"Soldier Token (White 1\/1) (Version 3)"},"3":{"idLanguage":3,"languageName":"German","productName":"Soldier Token (White 1\/1) (Version 3)"},"4":{"idLanguage":4,"languageName":"Spanish","productName":"Soldier Token (White 1\/1) (Version 3)"},"5":{"idLanguage":5,"languageName":"Italian","productName":"Soldier Token (White 1\/1) (Version 3)"}},"website":"\/Products\/Singles\/Tokens+for+MTG\/Soldier+Token+%28White+1%2F1%29+%28Version+3%29","image":".\/img\/cards\/Tokens_for_MTG\/soldier_token_white_113.jpg","category":{"idCategory":1,"categoryName":"Magic Single"},"expansion":"Tokens for MTG","expIcon":258,"number":null,"rarity":"Token"},{"idProduct":283668,"idMetaproduct":9112,"idGame":1,"countReprints":"10","name":{"1":{"idLanguage":1,"languageName":"English","productName":"Marit Lage Token (Black 20\/20)"},"2":{"idLanguage":2,"languageName":"French","productName":"Marit Lage Token (Black 20\/20)"},"3":{"idLanguage":3,"languageName":"German","productName":"Marit Lage Token (Black 20\/20)"},"4":{"idLanguage":4,"languageName":"Spanish","productName":"Marit Lage Token (Black 20\/20)"},"5":{"idLanguage":5,"languageName":"Italian","productName":"Marit Lage Token (Black 20\/20)"}},"website":"\/Products\/Singles\/Tokens+for+MTG\/Marit+Lage+Token+%28Black+20%2F20%29","image":".\/img\/cards\/Tokens_for_MTG\/marit_lage_token_black_2020.jpg","category":{"idCategory":1,"categoryName":"Magic Single"},"expansion":"Tokens for MTG","expIcon":258,"number":null,"rarity":"Token"},{"idProduct":283669,"idMetaproduct":210417,"idGame":1,"countReprints":"5","name":{"1":{"idLanguage":1,"languageName":"English","productName":"Morph Token (Colorless 2\/2)"},"2":{"idLanguage":2,"languageName":"French","productName":"Morph Token (Colorless 2\/2)"},"3":{"idLanguage":3,"languageName":"German","productName":"Morph Token (Colorless 2\/2)"},"4":{"idLanguage":4,"languageName":"Spanish","productName":"Morph Token (Colorless 2\/2)"},"5":{"idLanguage":5,"languageName":"Italian","productName":"Morph Token (Colorless 2\/2)"}},"website":"\/Products\/Singles\/Tokens+for+MTG\/Morph+Token+%28Colorless+2%2F2%29","image":".\/img\/cards\/Tokens_for_MTG\/morph_token_colorless_22.jpg","category":{"idCategory":1,"categoryName":"Magic Single"},"expansion":"Tokens for MTG","expIcon":258,"number":null,"rarity":"Token"},{"idProduct":284355,"idMetaproduct":206655,"idGame":1,"countReprints":"8","name":{"1":{"idLanguage":1,"languageName":"English","productName":"Knight Token (White 2\/2 Vigilance)"},"2":{"idLanguage":2,"languageName":"French","productName":"Knight Token (White 2\/2 Vigilance)"},"3":{"idLanguage":3,"languageName":"German","productName":"Knight Token (White 2\/2 Vigilance)"},"4":{"idLanguage":4,"languageName":"Spanish","productName":"Knight Token (White 2\/2 Vigilance)"},"5":{"idLanguage":5,"languageName":"Italian","productName":"Knight Token (White 2\/2 Vigilance)"}},"website":"\/Products\/Singles\/Tokens+for+MTG\/Knight+Token+%28White+2%2F2+Vigilance%29","image":".\/img\/cards\/Tokens_for_MTG\/knight_token_white_22_vigilance.jpg","category":{"idCategory":1,"categoryName":"Magic Single"},"expansion":"Tokens for MTG","expIcon":258,"number":null,"rarity":"Token"},{"idProduct":284356,"idMetaproduct":204199,"idGame":1,"countReprints":"11","name":{"1":{"idLanguage":1,"languageName":"English","productName":"Demon Token (Black 5\/5)"},"2":{"idLanguage":2,"languageName":"French","productName":"Demon Token (Black 5\/5)"},"3":{"idLanguage":3,"languageName":"German","productName":"Demon Token (Black 5\/5)"},"4":{"idLanguage":4,"languageName":"Spanish","productName":"Demon Token (Black 5\/5)"},"5":{"idLanguage":5,"languageName":"Italian","productName":"Demon Token (Black 5\/5)"}},"website":"\/Products\/Singles\/Tokens+for+MTG\/Demon+Token+%28Black+5%2F5%29","image":".\/img\/cards\/Tokens_for_MTG\/demon_token_black_55.jpg","category":{"idCategory":1,"categoryName":"Magic Single"},"expansion":"Tokens for MTG","expIcon":258,"number":null,"rarity":"Token"},{"idProduct":284359,"idMetaproduct":210233,"idGame":1,"countReprints":"6","name":{"1":{"idLanguage":1,"languageName":"English","productName":"Elemental Token (Green *\/*)"},"2":{"idLanguage":2,"languageName":"French","productName":"Elemental Token (Green *\/*)"},"3":{"idLanguage":3,"languageName":"German","productName":"Elemental Token (Green *\/*)"},"4":{"idLanguage":4,"languageName":"Spanish","productName":"Elemental Token (Green *\/*)"},"5":{"idLanguage":5,"languageName":"Italian","productName":"Elemental Token (Green *\/*)"}},"website":"\/Products\/Singles\/Tokens+for+MTG\/Elemental+Token+%28Green+%2A%2F%2A%29","image":".\/img\/cards\/Tokens_for_MTG\/elemental_token_green_xx.jpg","category":{"idCategory":1,"categoryName":"Magic Single"},"expansion":"Tokens for MTG","expIcon":258,"number":null,"rarity":"Token"},{"idProduct":284358,"idMetaproduct":210418,"idGame":1,"countReprints":"14","name":{"1":{"idLanguage":1,"languageName":"English","productName":"Warrior Token (White 1\/1) (Version 2)"},"2":{"idLanguage":2,"languageName":"French","productName":"Warrior Token (White 1\/1) (Version 2)"},"3":{"idLanguage":3,"languageName":"German","productName":"Warrior Token (White 1\/1) (Version 2)"},"4":{"idLanguage":4,"languageName":"Spanish","productName":"Warrior Token (White 1\/1) (Version 2)"},"5":{"idLanguage":5,"languageName":"Italian","productName":"Warrior Token (White 1\/1) (Version 2)"}},"website":"\/Products\/Singles\/Tokens+for+MTG\/Warrior+Token+%28White+1%2F1%29+%28Version+2%29","image":".\/img\/cards\/Tokens_for_MTG\/warrior_token_white_112.jpg","category":{"idCategory":1,"categoryName":"Magic Single"},"expansion":"Tokens for MTG","expIcon":258,"number":null,"rarity":"Token"},{"idProduct":285135,"idMetaproduct":9400,"idGame":1,"countReprints":"34","name":{"1":{"idLanguage":1,"languageName":"English","productName":"Beast Token (Green 3\/3) (Version 2)"},"2":{"idLanguage":2,"languageName":"French","productName":"Beast Token (Green 3\/3) (Version 2)"},"3":{"idLanguage":3,"languageName":"German","productName":"Beast Token (Green 3\/3) (Version 2)"},"4":{"idLanguage":4,"languageName":"Spanish","productName":"Beast Token (Green 3\/3) (Version 2)"},"5":{"idLanguage":5,"languageName":"Italian","productName":"Beast Token (Green 3\/3) (Version 2)"}},"website":"\/Products\/Singles\/Tokens+for+MTG\/Beast+Token+%28Green+3%2F3%29+%28Version+2%29","image":".\/img\/cards\/Tokens_for_MTG\/beast_token_green_332.jpg","category":{"idCategory":1,"categoryName":"Magic Single"},"expansion":"Tokens for MTG","expIcon":258,"number":null,"rarity":"Token"},{"idProduct":285136,"idMetaproduct":9397,"idGame":1,"countReprints":"31","name":{"1":{"idLanguage":1,"languageName":"English","productName":"Wolf Token (Green 2\/2) (Version 3)"},"2":{"idLanguage":2,"languageName":"French","productName":"Wolf Token (Green 2\/2) (Version 3)"},"3":{"idLanguage":3,"languageName":"German","productName":"Wolf Token (Green 2\/2) (Version 3)"},"4":{"idLanguage":4,"languageName":"Spanish","productName":"Wolf Token (Green 2\/2) (Version 3)"},"5":{"idLanguage":5,"languageName":"Italian","productName":"Wolf Token (Green 2\/2) (Version 3)"}},"website":"\/Products\/Singles\/Tokens+for+MTG\/Wolf+Token+%28Green+2%2F2%29+%28Version+3%29","image":".\/img\/cards\/Tokens_for_MTG\/wolf_token_green_223.jpg","category":{"idCategory":1,"categoryName":"Magic Single"},"expansion":"Tokens for MTG","expIcon":258,"number":null,"rarity":"Token"},{"idProduct":285137,"idMetaproduct":9102,"idGame":1,"countReprints":"55","name":{"1":{"idLanguage":1,"languageName":"English","productName":"Goblin Token (Red 1\/1) (Version 2)"},"2":{"idLanguage":2,"languageName":"French","productName":"Goblin Token (Red 1\/1) (Version 2)"},"3":{"idLanguage":3,"languageName":"German","productName":"Goblin Token (Red 1\/1) (Version 2)"},"4":{"idLanguage":4,"languageName":"Spanish","productName":"Goblin Token (Red 1\/1) (Version 2)"},"5":{"idLanguage":5,"languageName":"Italian","productName":"Goblin Token (Red 1\/1) (Version 2)"}},"website":"\/Products\/Singles\/Tokens+for+MTG\/Goblin+Token+%28Red+1%2F1%29+%28Version+2%29","image":".\/img\/cards\/Tokens_for_MTG\/goblin_token_red_112.jpg","category":{"idCategory":1,"categoryName":"Magic Single"},"expansion":"Tokens for MTG","expIcon":258,"number":null,"rarity":"Token"},{"idProduct":285140,"idMetaproduct":200756,"idGame":1,"countReprints":"11","name":{"1":{"idLanguage":1,"languageName":"English","productName":"Poison Counter"},"2":{"idLanguage":2,"languageName":"French","productName":"Poison Counter"},"3":{"idLanguage":3,"languageName":"German","productName":"Poison Counter"},"4":{"idLanguage":4,"languageName":"Spanish","productName":"Poison Counter"},"5":{"idLanguage":5,"languageName":"Italian","productName":"Poison Counter"}},"website":"\/Products\/Singles\/Tokens+for+MTG\/Poison+Counter","image":".\/img\/cards\/Tokens_for_MTG\/poison_counter.jpg","category":{"idCategory":1,"categoryName":"Magic Single"},"expansion":"Tokens for MTG","expIcon":258,"number":null,"rarity":"Token"},{"idProduct":285134,"idMetaproduct":220704,"idGame":1,"countReprints":"24","name":{"1":{"idLanguage":1,"languageName":"English","productName":"Eldrazi Scion Token (Colorless 1\/1)"},"2":{"idLanguage":2,"languageName":"French","productName":"Eldrazi Scion Token (Colorless 1\/1)"},"3":{"idLanguage":3,"languageName":"German","productName":"Eldrazi Scion Token (Colorless 1\/1)"},"4":{"idLanguage":4,"languageName":"Spanish","productName":"Eldrazi Scion Token (Colorless 1\/1)"},"5":{"idLanguage":5,"languageName":"Italian","productName":"Eldrazi Scion Token (Colorless 1\/1)"}},"website":"\/Products\/Singles\/Tokens+for+MTG\/Eldrazi+Scion+Token+%28Colorless+1%2F1%29","image":".\/img\/cards\/Tokens_for_MTG\/eldrazi_scion_token_colorless_11.jpg","category":{"idCategory":1,"categoryName":"Magic Single"},"expansion":"Tokens for MTG","expIcon":258,"number":null,"rarity":"Token"},{"idProduct":285138,"idMetaproduct":220706,"idGame":1,"countReprints":"11","name":{"1":{"idLanguage":1,"languageName":"English","productName":"Knight Ally Token (White 2\/2)"},"2":{"idLanguage":2,"languageName":"French","productName":"Knight Ally Token (White 2\/2)"},"3":{"idLanguage":3,"languageName":"German","productName":"Knight Ally Token (White 2\/2)"},"4":{"idLanguage":4,"languageName":"Spanish","productName":"Knight Ally Token (White 2\/2)"},"5":{"idLanguage":5,"languageName":"Italian","productName":"Knight Ally Token (White 2\/2)"}},"website":"\/Products\/Singles\/Tokens+for+MTG\/Knight+Ally+Token+%28White+2%2F2%29","image":".\/img\/cards\/Tokens_for_MTG\/knight_ally_token_white_22.jpg","category":{"idCategory":1,"categoryName":"Magic Single"},"expansion":"Tokens for MTG","expIcon":258,"number":null,"rarity":"Token"},{"idProduct":285139,"idMetaproduct":202516,"idGame":1,"countReprints":"23","name":{"1":{"idLanguage":1,"languageName":"English","productName":"Thopter Token (Artifact 1\/1)"},"2":{"idLanguage":2,"languageName":"French","productName":"Thopter Token (Artifact 1\/1)"},"3":{"idLanguage":3,"languageName":"German","productName":"Thopter Token (Artifact 1\/1)"},"4":{"idLanguage":4,"languageName":"Spanish","productName":"Thopter Token (Artifact 1\/1)"},"5":{"idLanguage":5,"languageName":"Italian","productName":"Thopter Token (Artifact 1\/1)"}},"website":"\/Products\/Singles\/Tokens+for+MTG\/Thopter+Token+%28Artifact+1%2F1%29","image":".\/img\/cards\/Tokens_for_MTG\/thopter_token_artifact_11.jpg","category":{"idCategory":1,"categoryName":"Magic Single"},"expansion":"Tokens for MTG","expIcon":258,"number":null,"rarity":"Token"},{"idProduct":285563,"idMetaproduct":220932,"idGame":1,"countReprints":"2","name":{"1":{"idLanguage":1,"languageName":"English","productName":"White Mana Counter"},"2":{"idLanguage":2,"languageName":"French","productName":"White Mana Counter"},"3":{"idLanguage":3,"languageName":"German","productName":"White Mana Counter"},"4":{"idLanguage":4,"languageName":"Spanish","productName":"White Mana Counter"},"5":{"idLanguage":5,"languageName":"Italian","productName":"White Mana Counter"}},"website":"\/Products\/Singles\/Tokens+for+MTG\/White+Mana+Counter","image":".\/img\/cards\/Tokens_for_MTG\/white_mana_counter.jpg","category":{"idCategory":1,"categoryName":"Magic Single"},"expansion":"Tokens for MTG","expIcon":258,"number":null,"rarity":"Token"},{"idProduct":285564,"idMetaproduct":220933,"idGame":1,"countReprints":"2","name":{"1":{"idLanguage":1,"languageName":"English","productName":"Blue Mana Counter"},"2":{"idLanguage":2,"languageName":"French","productName":"Blue Mana Counter"},"3":{"idLanguage":3,"languageName":"German","productName":"Blue Mana Counter"},"4":{"idLanguage":4,"languageName":"Spanish","productName":"Blue Mana Counter"},"5":{"idLanguage":5,"languageName":"Italian","productName":"Blue Mana Counter"}},"website":"\/Products\/Singles\/Tokens+for+MTG\/Blue+Mana+Counter","image":".\/img\/cards\/Tokens_for_MTG\/blue_mana_counter.jpg","category":{"idCategory":1,"categoryName":"Magic Single"},"expansion":"Tokens for MTG","expIcon":258,"number":null,"rarity":"Token"},{"idProduct":285565,"idMetaproduct":220934,"idGame":1,"countReprints":"2","name":{"1":{"idLanguage":1,"languageName":"English","productName":"Black Mana Counter"},"2":{"idLanguage":2,"languageName":"French","productName":"Black Mana Counter"},"3":{"idLanguage":3,"languageName":"German","productName":"Black Mana Counter"},"4":{"idLanguage":4,"languageName":"Spanish","productName":"Black Mana Counter"},"5":{"idLanguage":5,"languageName":"Italian","productName":"Black Mana Counter"}},"website":"\/Products\/Singles\/Tokens+for+MTG\/Black+Mana+Counter","image":".\/img\/cards\/Tokens_for_MTG\/black_mana_counter.jpg","category":{"idCategory":1,"categoryName":"Magic Single"},"expansion":"Tokens for MTG","expIcon":258,"number":null,"rarity":"Token"},{"idProduct":285566,"idMetaproduct":220935,"idGame":1,"countReprints":"2","name":{"1":{"idLanguage":1,"languageName":"English","productName":"Red Mana Counter"},"2":{"idLanguage":2,"languageName":"French","productName":"Red Mana Counter"},"3":{"idLanguage":3,"languageName":"German","productName":"Red Mana Counter"},"4":{"idLanguage":4,"languageName":"Spanish","productName":"Red Mana Counter"},"5":{"idLanguage":5,"languageName":"Italian","productName":"Red Mana Counter"}},"website":"\/Products\/Singles\/Tokens+for+MTG\/Red+Mana+Counter","image":".\/img\/cards\/Tokens_for_MTG\/red_mana_counter.jpg","category":{"idCategory":1,"categoryName":"Magic Single"},"expansion":"Tokens for MTG","expIcon":258,"number":null,"rarity":"Token"},{"idProduct":285567,"idMetaproduct":220936,"idGame":1,"countReprints":"2","name":{"1":{"idLanguage":1,"languageName":"English","productName":"Green Mana Counter"},"2":{"idLanguage":2,"languageName":"French","productName":"Green Mana Counter"},"3":{"idLanguage":3,"languageName":"German","productName":"Green Mana Counter"},"4":{"idLanguage":4,"languageName":"Spanish","productName":"Green Mana Counter"},"5":{"idLanguage":5,"languageName":"Italian","productName":"Green Mana Counter"}},"website":"\/Products\/Singles\/Tokens+for+MTG\/Green+Mana+Counter","image":".\/img\/cards\/Tokens_for_MTG\/green_mana_counter.jpg","category":{"idCategory":1,"categoryName":"Magic Single"},"expansion":"Tokens for MTG","expIcon":258,"number":null,"rarity":"Token"},{"idProduct":285568,"idMetaproduct":220937,"idGame":1,"countReprints":"3","name":{"1":{"idLanguage":1,"languageName":"English","productName":"Storm Counter"},"2":{"idLanguage":2,"languageName":"French","productName":"Storm Counter"},"3":{"idLanguage":3,"languageName":"German","productName":"Storm Counter"},"4":{"idLanguage":4,"languageName":"Spanish","productName":"Storm Counter"},"5":{"idLanguage":5,"languageName":"Italian","productName":"Storm Counter"}},"website":"\/Products\/Singles\/Tokens+for+MTG\/Storm+Counter","image":".\/img\/cards\/Tokens_for_MTG\/storm_counter.jpg","category":{"idCategory":1,"categoryName":"Magic Single"},"expansion":"Tokens for MTG","expIcon":258,"number":null,"rarity":"Token"},{"idProduct":286478,"idMetaproduct":11008,"idGame":1,"countReprints":"17","name":{"1":{"idLanguage":1,"languageName":"English","productName":"Plant Token (Green 0\/1) (Version 1)"},"2":{"idLanguage":2,"languageName":"French","productName":"Plant Token (Green 0\/1) (Version 1)"},"3":{"idLanguage":3,"languageName":"German","productName":"Plant Token (Green 0\/1) (Version 1)"},"4":{"idLanguage":4,"languageName":"Spanish","productName":"Plant Token (Green 0\/1) (Version 1)"},"5":{"idLanguage":5,"languageName":"Italian","productName":"Plant Token (Green 0\/1) (Version 1)"}},"website":"\/Products\/Singles\/Tokens+for+MTG\/Plant+Token+%28Green+0%2F1%29+%28Version+1%29","image":".\/img\/cards\/Tokens_for_MTG\/plant_token_green_011.jpg","category":{"idCategory":1,"categoryName":"Magic Single"},"expansion":"Tokens for MTG","expIcon":258,"number":null,"rarity":"Token"},{"idProduct":286477,"idMetaproduct":10812,"idGame":1,"countReprints":"8","name":{"1":{"idLanguage":1,"languageName":"English","productName":"Snake Token (Green 1\/1)"},"2":{"idLanguage":2,"languageName":"French","productName":"Snake Token (Green 1\/1)"},"3":{"idLanguage":3,"languageName":"German","productName":"Snake Token (Green 1\/1)"},"4":{"idLanguage":4,"languageName":"Spanish","productName":"Snake Token (Green 1\/1)"},"5":{"idLanguage":5,"languageName":"Italian","productName":"Snake Token (Green 1\/1)"}},"website":"\/Products\/Singles\/Tokens+for+MTG\/Snake+Token+%28Green+1%2F1%29","image":".\/img\/cards\/Tokens_for_MTG\/snake_token_green_11.jpg","category":{"idCategory":1,"categoryName":"Magic Single"},"expansion":"Tokens for MTG","expIcon":258,"number":null,"rarity":"Token"},{"idProduct":286479,"idMetaproduct":9107,"idGame":1,"countReprints":"78","name":{"1":{"idLanguage":1,"languageName":"English","productName":"Zombie Token (Black 2\/2) (Version 3)"},"2":{"idLanguage":2,"languageName":"French","productName":"Zombie Token (Black 2\/2) (Version 3)"},"3":{"idLanguage":3,"languageName":"German","productName":"Zombie Token (Black 2\/2) (Version 3)"},"4":{"idLanguage":4,"languageName":"Spanish","productName":"Zombie Token (Black 2\/2) (Version 3)"},"5":{"idLanguage":5,"languageName":"Italian","productName":"Zombie Token (Black 2\/2) (Version 3)"}},"website":"\/Products\/Singles\/Tokens+for+MTG\/Zombie+Token+%28Black+2%2F2%29+%28Version+3%29","image":".\/img\/cards\/Tokens_for_MTG\/zombie_token_black_223.jpg","category":{"idCategory":1,"categoryName":"Magic Single"},"expansion":"Tokens for MTG","expIcon":258,"number":null,"rarity":"Token"},{"idProduct":287770,"idMetaproduct":10032,"idGame":1,"countReprints":"3","name":{"1":{"idLanguage":1,"languageName":"English","productName":"Bird Token (Blue 1\/1)"},"2":{"idLanguage":2,"languageName":"French","productName":"Bird Token (Blue 1\/1)"},"3":{"idLanguage":3,"languageName":"German","productName":"Bird Token (Blue 1\/1)"},"4":{"idLanguage":4,"languageName":"Spanish","productName":"Bird Token (Blue 1\/1)"},"5":{"idLanguage":5,"languageName":"Italian","productName":"Bird Token (Blue 1\/1)"}},"website":"\/Products\/Singles\/Tokens+for+MTG\/Bird+Token+%28Blue+1%2F1%29","image":".\/img\/cards\/Tokens_for_MTG\/bird_token_blue_11.jpg","category":{"idCategory":1,"categoryName":"Magic Single"},"expansion":"Tokens for MTG","expIcon":258,"number":null,"rarity":"Token"},{"idProduct":287771,"idMetaproduct":208106,"idGame":1,"countReprints":"3","name":{"1":{"idLanguage":1,"languageName":"English","productName":"Bat Token (Black 1\/1)"},"2":{"idLanguage":2,"languageName":"French","productName":"Bat Token (Black 1\/1)"},"3":{"idLanguage":3,"languageName":"German","productName":"Bat Token (Black 1\/1)"},"4":{"idLanguage":4,"languageName":"Spanish","productName":"Bat Token (Black 1\/1)"},"5":{"idLanguage":5,"languageName":"Italian","productName":"Bat Token (Black 1\/1)"}},"website":"\/Products\/Singles\/Tokens+for+MTG\/Bat+Token+%28Black+1%2F1%29","image":".\/img\/cards\/Tokens_for_MTG\/bat_token_black_11.jpg","category":{"idCategory":1,"categoryName":"Magic Single"},"expansion":"Tokens for MTG","expIcon":258,"number":null,"rarity":"Token"},{"idProduct":287772,"idMetaproduct":9408,"idGame":1,"countReprints":"9","name":{"1":{"idLanguage":1,"languageName":"English","productName":"Bear Token (Green 2\/2)"},"2":{"idLanguage":2,"languageName":"French","productName":"Bear Token (Green 4\/4)"},"3":{"idLanguage":3,"languageName":"German","productName":"Bear Token (Green 4\/4)"},"4":{"idLanguage":4,"languageName":"Spanish","productName":"Bear Token (Green 4\/4)"},"5":{"idLanguage":5,"languageName":"Italian","productName":"Bear Token (Green 4\/4)"}},"website":"\/Products\/Singles\/Tokens+for+MTG\/Bear+Token+%28Green+2%2F2%29","image":".\/img\/cards\/Tokens_for_MTG\/bear_token_green_22.jpg","category":{"idCategory":1,"categoryName":"Magic Single"},"expansion":"Tokens for MTG","expIcon":258,"number":null,"rarity":"Token"},{"idProduct":287773,"idMetaproduct":220703,"idGame":1,"countReprints":"9","name":{"1":{"idLanguage":1,"languageName":"English","productName":"Octopus Token (Blue 8\/8)"},"2":{"idLanguage":2,"languageName":"French","productName":"Octopus Token (Blue 8\/8)"},"3":{"idLanguage":3,"languageName":"German","productName":"Octopus Token (Blue 8\/8)"},"4":{"idLanguage":4,"languageName":"Spanish","productName":"Octopus Token (Blue 8\/8)"},"5":{"idLanguage":5,"languageName":"Italian","productName":"Octopus Token (Blue 8\/8)"}},"website":"\/Products\/Singles\/Tokens+for+MTG\/Octopus+Token+%28Blue+8%2F8%29","image":".\/img\/cards\/Tokens_for_MTG\/octopus_token_blue_88.jpg","category":{"idCategory":1,"categoryName":"Magic Single"},"expansion":"Tokens for MTG","expIcon":258,"number":null,"rarity":"Token"},{"idProduct":287774,"idMetaproduct":221630,"idGame":1,"countReprints":"6","name":{"1":{"idLanguage":1,"languageName":"English","productName":"Elemental Token (Red 3\/1 Haste)"},"2":{"idLanguage":2,"languageName":"French","productName":"Elemental Token (Red 3\/1 Haste)"},"3":{"idLanguage":3,"languageName":"German","productName":"Elemental Token (Red 3\/1 Haste)"},"4":{"idLanguage":4,"languageName":"Spanish","productName":"Elemental Token (Red 3\/1 Haste)"},"5":{"idLanguage":5,"languageName":"Italian","productName":"Elemental Token (Red 3\/1 Haste)"}},"website":"\/Products\/Singles\/Tokens+for+MTG\/Elemental+Token+%28Red+3%2F1+Haste%29","image":".\/img\/cards\/Tokens_for_MTG\/elemental_token_red_31_haste.jpg","category":{"idCategory":1,"categoryName":"Magic Single"},"expansion":"Tokens for MTG","expIcon":258,"number":null,"rarity":"Token"},{"idProduct":289293,"idMetaproduct":222210,"idGame":1,"countReprints":"4","name":{"1":{"idLanguage":1,"languageName":"English","productName":"Devil Token (Red 1\/1)"},"2":{"idLanguage":2,"languageName":"French","productName":"Devil Token (Red 1\/1)"},"3":{"idLanguage":3,"languageName":"German","productName":"Devil Token (Red 1\/1)"},"4":{"idLanguage":4,"languageName":"Spanish","productName":"Devil Token (Red 1\/1)"},"5":{"idLanguage":5,"languageName":"Italian","productName":"Devil Token (Red 1\/1)"}},"website":"\/Products\/Singles\/Tokens+for+MTG\/Devil+Token+%28Red+1%2F1%29","image":".\/img\/cards\/Tokens_for_MTG\/devil_token_red_11.jpg","category":{"idCategory":1,"categoryName":"Magic Single"},"expansion":"Tokens for MTG","expIcon":258,"number":null,"rarity":"Token"},{"idProduct":289295,"idMetaproduct":9416,"idGame":1,"countReprints":"11","name":{"1":{"idLanguage":1,"languageName":"English","productName":"Myr Token (Artifact 1\/1)"},"2":{"idLanguage":2,"languageName":"French","productName":"Myr Token (Artifact 1\/1)"},"3":{"idLanguage":3,"languageName":"German","productName":"Myr Token (Artifact 1\/1)"},"4":{"idLanguage":4,"languageName":"Spanish","productName":"Myr Token (Artifact 1\/1)"},"5":{"idLanguage":5,"languageName":"Italian","productName":"Myr Token (Artifact 1\/1)"}},"website":"\/Products\/Singles\/Tokens+for+MTG\/Myr+Token+%28Artifact+1%2F1%29","image":".\/img\/cards\/Tokens_for_MTG\/myr_token_artifact_11.jpg","category":{"idCategory":1,"categoryName":"Magic Single"},"expansion":"Tokens for MTG","expIcon":258,"number":null,"rarity":"Token"},{"idProduct":289292,"idMetaproduct":222206,"idGame":1,"countReprints":"19","name":{"1":{"idLanguage":1,"languageName":"English","productName":"Clue Token"},"2":{"idLanguage":2,"languageName":"French","productName":"Clue Token"},"3":{"idLanguage":3,"languageName":"German","productName":"Clue Token"},"4":{"idLanguage":4,"languageName":"Spanish","productName":"Clue Token"},"5":{"idLanguage":5,"languageName":"Italian","productName":"Clue Token"}},"website":"\/Products\/Singles\/Tokens+for+MTG\/Clue+Token","image":".\/img\/cards\/Tokens_for_MTG\/clue_token.jpg","category":{"idCategory":1,"categoryName":"Magic Single"},"expansion":"Tokens for MTG","expIcon":258,"number":null,"rarity":"Token"},{"idProduct":289294,"idMetaproduct":220707,"idGame":1,"countReprints":"6","name":{"1":{"idLanguage":1,"languageName":"English","productName":"Kor Ally Token (White 1\/1)"},"2":{"idLanguage":2,"languageName":"French","productName":"Kor Ally Token (White 1\/1)"},"3":{"idLanguage":3,"languageName":"German","productName":"Kor Ally Token (White 1\/1)"},"4":{"idLanguage":4,"languageName":"Spanish","productName":"Kor Ally Token (White 1\/1)"},"5":{"idLanguage":5,"languageName":"Italian","productName":"Kor Ally Token (White 1\/1)"}},"website":"\/Products\/Singles\/Tokens+for+MTG\/Kor+Ally+Token+%28White+1%2F1%29","image":".\/img\/cards\/Tokens_for_MTG\/kor_ally_token_white_11.jpg","category":{"idCategory":1,"categoryName":"Magic Single"},"expansion":"Tokens for MTG","expIcon":258,"number":null,"rarity":"Token"},{"idProduct":289296,"idMetaproduct":204897,"idGame":1,"countReprints":"9","name":{"1":{"idLanguage":1,"languageName":"English","productName":"Vampire Token (Black 1\/1 Lifelink)"},"2":{"idLanguage":2,"languageName":"French","productName":"Vampire Token (Black 1\/1 Lifelink)"},"3":{"idLanguage":3,"languageName":"German","productName":"Vampire Token (Black 1\/1 Lifelink)"},"4":{"idLanguage":4,"languageName":"Spanish","productName":"Vampire Token (Black 1\/1 Lifelink)"},"5":{"idLanguage":5,"languageName":"Italian","productName":"Vampire Token (Black 1\/1 Lifelink)"}},"website":"\/Products\/Singles\/Tokens+for+MTG\/Vampire+Token+%28Black+1%2F1+Lifelink%29","image":".\/img\/cards\/Tokens_for_MTG\/vampire_token_black_11_lifelink.jpg","category":{"idCategory":1,"categoryName":"Magic Single"},"expansion":"Tokens for MTG","expIcon":258,"number":null,"rarity":"Token"},{"idProduct":291392,"idMetaproduct":208830,"idGame":1,"countReprints":"2","name":{"1":{"idLanguage":1,"languageName":"English","productName":"Boar Token (Green 2\/2)"},"2":{"idLanguage":2,"languageName":"French","productName":"Boar Token (Green 2\/2)"},"3":{"idLanguage":3,"languageName":"German","productName":"Boar Token (Green 2\/2)"},"4":{"idLanguage":4,"languageName":"Spanish","productName":"Boar Token (Green 2\/2)"},"5":{"idLanguage":5,"languageName":"Italian","productName":"Boar Token (Green 2\/2)"}},"website":"\/Products\/Singles\/Tokens+for+MTG\/Boar+Token+%28Green+2%2F2%29","image":".\/img\/cards\/Tokens_for_MTG\/boar_token_green_22.jpg","category":{"idCategory":1,"categoryName":"Magic Single"},"expansion":"Tokens for MTG","expIcon":258,"number":null,"rarity":"Token"},{"idProduct":291393,"idMetaproduct":9396,"idGame":1,"countReprints":"25","name":{"1":{"idLanguage":1,"languageName":"English","productName":"Elf Warrior Token (Green 1\/1)"},"2":{"idLanguage":2,"languageName":"French","productName":"Elf Warrior Token (Green 1\/1)"},"3":{"idLanguage":3,"languageName":"German","productName":"Elf Warrior Token (Green 1\/1)"},"4":{"idLanguage":4,"languageName":"Spanish","productName":"Elf Warrior Token (Green 1\/1)"},"5":{"idLanguage":5,"languageName":"Italian","productName":"Elf Warrior Token (Green 1\/1)"}},"website":"\/Products\/Singles\/Tokens+for+MTG\/Elf+Warrior+Token+%28Green+1%2F1%29","image":".\/img\/cards\/Tokens_for_MTG\/elf_warrior_token_green_11.jpg","category":{"idCategory":1,"categoryName":"Magic Single"},"expansion":"Tokens for MTG","expIcon":258,"number":null,"rarity":"Token"},{"idProduct":291394,"idMetaproduct":204896,"idGame":1,"countReprints":"10","name":{"1":{"idLanguage":1,"languageName":"English","productName":"Human Token (White 1\/1)"},"2":{"idLanguage":2,"languageName":"French","productName":"Human Token (White 1\/1)"},"3":{"idLanguage":3,"languageName":"German","productName":"Human Token (White 1\/1)"},"4":{"idLanguage":4,"languageName":"Spanish","productName":"Human Token (White 1\/1)"},"5":{"idLanguage":5,"languageName":"Italian","productName":"Human Token (White 1\/1)"}},"website":"\/Products\/Singles\/Tokens+for+MTG\/Human+Token+%28White+1%2F1%29","image":".\/img\/cards\/Tokens_for_MTG\/human_token_white_11.jpg","category":{"idCategory":1,"categoryName":"Magic Single"},"expansion":"Tokens for MTG","expIcon":258,"number":null,"rarity":"Token"},{"idProduct":291395,"idMetaproduct":9103,"idGame":1,"countReprints":"4","name":{"1":{"idLanguage":1,"languageName":"English","productName":"Pegasus Token (White 1\/1)"},"2":{"idLanguage":2,"languageName":"French","productName":"Pegasus Token (White 1\/1)"},"3":{"idLanguage":3,"languageName":"German","productName":"Pegasus Token (White 1\/1)"},"4":{"idLanguage":4,"languageName":"Spanish","productName":"Pegasus Token (White 1\/1)"},"5":{"idLanguage":5,"languageName":"Italian","productName":"Pegasus Token (White 1\/1)"}},"website":"\/Products\/Singles\/Tokens+for+MTG\/Pegasus+Token+%28White+1%2F1%29","image":".\/img\/cards\/Tokens_for_MTG\/pegasus_token_white_11.jpg","category":{"idCategory":1,"categoryName":"Magic Single"},"expansion":"Tokens for MTG","expIcon":258,"number":null,"rarity":"Token"},{"idProduct":291396,"idMetaproduct":9405,"idGame":1,"countReprints":"21","name":{"1":{"idLanguage":1,"languageName":"English","productName":"Elephant Token (Green 3\/3)"},"2":{"idLanguage":2,"languageName":"French","productName":"Elephant Token (Green 3\/3)"},"3":{"idLanguage":3,"languageName":"German","productName":"Elephant Token (Green 3\/3)"},"4":{"idLanguage":4,"languageName":"Spanish","productName":"Elephant Token (Green 3\/3)"},"5":{"idLanguage":5,"languageName":"Italian","productName":"Elephant Token (Green 3\/3)"}},"website":"\/Products\/Singles\/Tokens+for+MTG\/Elephant+Token+%28Green+3%2F3%29","image":".\/img\/cards\/Tokens_for_MTG\/elephant_token_green_33.jpg","category":{"idCategory":1,"categoryName":"Magic Single"},"expansion":"Tokens for MTG","expIcon":258,"number":null,"rarity":"Token"},{"idProduct":293193,"idMetaproduct":210231,"idGame":1,"countReprints":"7","name":{"1":{"idLanguage":1,"languageName":"English","productName":"Pack Rat Token (Black *\/*)"},"2":{"idLanguage":2,"languageName":"French","productName":"Pack Rat Token (Black *\/*)"},"3":{"idLanguage":3,"languageName":"German","productName":"Pack Rat Token (Black *\/*)"},"4":{"idLanguage":4,"languageName":"Spanish","productName":"Pack Rat Token (Black *\/*)"},"5":{"idLanguage":5,"languageName":"Italian","productName":"Pack Rat Token (Black *\/*)"}},"website":"\/Products\/Singles\/Tokens+for+MTG\/Pack+Rat+Token+%28Black+%2A%2F%2A%29","image":".\/img\/cards\/Tokens_for_MTG\/pack_rat_token_black_xx.jpg","category":{"idCategory":1,"categoryName":"Magic Single"},"expansion":"Tokens for MTG","expIcon":258,"number":null,"rarity":"Token"},{"idProduct":293194,"idMetaproduct":9844,"idGame":1,"countReprints":"12","name":{"1":{"idLanguage":1,"languageName":"English","productName":"Spider Token (Green 1\/2)"},"2":{"idLanguage":2,"languageName":"French","productName":"Spider Token (Green 1\/2)"},"3":{"idLanguage":3,"languageName":"German","productName":"Spider Token (Green 1\/2)"},"4":{"idLanguage":4,"languageName":"Spanish","productName":"Spider Token (Green 1\/2)"},"5":{"idLanguage":5,"languageName":"Italian","productName":"Spider Token (Green 1\/2)"}},"website":"\/Products\/Singles\/Tokens+for+MTG\/Spider+Token+%28Green+1%2F2%29","image":".\/img\/cards\/Tokens_for_MTG\/spider_token_green_12.jpg","category":{"idCategory":1,"categoryName":"Magic Single"},"expansion":"Tokens for MTG","expIcon":258,"number":null,"rarity":"Token"},{"idProduct":293198,"idMetaproduct":223897,"idGame":1,"countReprints":"9","name":{"1":{"idLanguage":1,"languageName":"English","productName":"Energy Reserve"},"2":{"idLanguage":2,"languageName":"French","productName":"Energy Reserve"},"3":{"idLanguage":3,"languageName":"German","productName":"Energy Reserve"},"4":{"idLanguage":4,"languageName":"Spanish","productName":"Energy Reserve"},"5":{"idLanguage":5,"languageName":"Italian","productName":"Energy Reserve"}},"website":"\/Products\/Singles\/Tokens+for+MTG\/Energy+Reserve","image":".\/img\/cards\/Tokens_for_MTG\/energy_reserve.jpg","category":{"idCategory":1,"categoryName":"Magic Single"},"expansion":"Tokens for MTG","expIcon":258,"number":null,"rarity":"Token"},{"idProduct":291397,"idMetaproduct":222212,"idGame":1,"countReprints":"7","name":{"1":{"idLanguage":1,"languageName":"English","productName":"Human Cleric Token (White and Black 1\/1)"},"2":{"idLanguage":2,"languageName":"French","productName":"Human Cleric Token (White and Black 1\/1)"},"3":{"idLanguage":3,"languageName":"German","productName":"Human Cleric Token (White and Black 1\/1)"},"4":{"idLanguage":4,"languageName":"Spanish","productName":"Human Cleric Token (White and Black 1\/1)"},"5":{"idLanguage":5,"languageName":"Italian","productName":"Human Cleric Token (White and Black 1\/1)"}},"website":"\/Products\/Singles\/Tokens+for+MTG\/Human+Cleric+Token+%28White+and+Black+1%2F1%29","image":".\/img\/cards\/Tokens_for_MTG\/human_cleric_token_white_and_black_11.jpg","category":{"idCategory":1,"categoryName":"Magic Single"},"expansion":"Tokens for MTG","expIcon":258,"number":null,"rarity":"Token"},{"idProduct":291398,"idMetaproduct":222209,"idGame":1,"countReprints":"8","name":{"1":{"idLanguage":1,"languageName":"English","productName":"Vampire Knight Token (Black 1\/1)"},"2":{"idLanguage":2,"languageName":"French","productName":"Vampire Knight Token (Black 1\/1)"},"3":{"idLanguage":3,"languageName":"German","productName":"Vampire Knight Token (Black 1\/1)"},"4":{"idLanguage":4,"languageName":"Spanish","productName":"Vampire Knight Token (Black 1\/1)"},"5":{"idLanguage":5,"languageName":"Italian","productName":"Vampire Knight Token (Black 1\/1)"}},"website":"\/Products\/Singles\/Tokens+for+MTG\/Vampire+Knight+Token+%28Black+1%2F1%29","image":".\/img\/cards\/Tokens_for_MTG\/vampire_knight_token_black_11.jpg","category":{"idCategory":1,"categoryName":"Magic Single"},"expansion":"Tokens for MTG","expIcon":258,"number":null,"rarity":"Token"},{"idProduct":291399,"idMetaproduct":223048,"idGame":1,"countReprints":"5","name":{"1":{"idLanguage":1,"languageName":"English","productName":"Eldrazi Horror Token (Colorless 3\/2)"},"2":{"idLanguage":2,"languageName":"French","productName":"Eldrazi Horror Token (Colorless 3\/2)"},"3":{"idLanguage":3,"languageName":"German","productName":"Eldrazi Horror Token (Colorless 3\/2)"},"4":{"idLanguage":4,"languageName":"Spanish","productName":"Eldrazi Horror Token (Colorless 3\/2)"},"5":{"idLanguage":5,"languageName":"Italian","productName":"Eldrazi Horror Token (Colorless 3\/2)"}},"website":"\/Products\/Singles\/Tokens+for+MTG\/Eldrazi+Horror+Token+%28Colorless+3%2F2%29","image":".\/img\/cards\/Tokens_for_MTG\/eldrazi_horror_token_colorless_32.jpg","category":{"idCategory":1,"categoryName":"Magic Single"},"expansion":"Tokens for MTG","expIcon":258,"number":null,"rarity":"Token"},{"idProduct":293195,"idMetaproduct":223783,"idGame":1,"countReprints":"12","name":{"1":{"idLanguage":1,"languageName":"English","productName":"Servo Token (Artifact 1\/1)"},"2":{"idLanguage":2,"languageName":"French","productName":"Servo Token (Artifact 1\/1)"},"3":{"idLanguage":3,"languageName":"German","productName":"Servo Token (Artifact 1\/1)"},"4":{"idLanguage":4,"languageName":"Spanish","productName":"Servo Token (Artifact 1\/1)"},"5":{"idLanguage":5,"languageName":"Italian","productName":"Servo Token (Artifact 1\/1)"}},"website":"\/Products\/Singles\/Tokens+for+MTG\/Servo+Token+%28Artifact+1%2F1%29","image":".\/img\/cards\/Tokens_for_MTG\/servo_token_artifact_11.jpg","category":{"idCategory":1,"categoryName":"Magic Single"},"expansion":"Tokens for MTG","expIcon":258,"number":null,"rarity":"Token"},{"idProduct":293196,"idMetaproduct":223782,"idGame":1,"countReprints":"6","name":{"1":{"idLanguage":1,"languageName":"English","productName":"Construct Token (Artifact *\/*)"},"2":{"idLanguage":2,"languageName":"French","productName":"Construct Token (Artifact *\/*)"},"3":{"idLanguage":3,"languageName":"German","productName":"Construct Token (Artifact *\/*)"},"4":{"idLanguage":4,"languageName":"Spanish","productName":"Construct Token (Artifact *\/*)"},"5":{"idLanguage":5,"languageName":"Italian","productName":"Construct Token (Artifact *\/*)"}},"website":"\/Products\/Singles\/Tokens+for+MTG\/Construct+Token+%28Artifact+%2A%2F%2A%29","image":".\/img\/cards\/Tokens_for_MTG\/construct_token_artifact_xx.jpg","category":{"idCategory":1,"categoryName":"Magic Single"},"expansion":"Tokens for MTG","expIcon":258,"number":null,"rarity":"Token"},{"idProduct":295513,"idMetaproduct":200457,"idGame":1,"countReprints":"2","name":{"1":{"idLanguage":1,"languageName":"English","productName":"Ooze Token (Green 1\/1)"},"2":{"idLanguage":2,"languageName":"French","productName":"Ooze Token (Green 1\/1)"},"3":{"idLanguage":3,"languageName":"German","productName":"Ooze Token (Green 1\/1)"},"4":{"idLanguage":4,"languageName":"Spanish","productName":"Ooze Token (Green 1\/1)"},"5":{"idLanguage":5,"languageName":"Italian","productName":"Ooze Token (Green 1\/1)"}},"website":"\/Products\/Singles\/Tokens+for+MTG\/Ooze+Token+%28Green+1%2F1%29","image":".\/img\/cards\/Tokens_for_MTG\/ooze_token_green_11.jpg","category":{"idCategory":1,"categoryName":"Magic Single"},"expansion":"Tokens for MTG","expIcon":258,"number":null,"rarity":"Token"},{"idProduct":295514,"idMetaproduct":200456,"idGame":1,"countReprints":"2","name":{"1":{"idLanguage":1,"languageName":"English","productName":"Ooze Token (Green 2\/2)"},"2":{"idLanguage":2,"languageName":"French","productName":"Ooze Token (Green 2\/2)"},"3":{"idLanguage":3,"languageName":"German","productName":"Ooze Token (Green 2\/2)"},"4":{"idLanguage":4,"languageName":"Spanish","productName":"Ooze Token (Green 2\/2)"},"5":{"idLanguage":5,"languageName":"Italian","productName":"Ooze Token (Green 2\/2)"}},"website":"\/Products\/Singles\/Tokens+for+MTG\/Ooze+Token+%28Green+2%2F2%29","image":".\/img\/cards\/Tokens_for_MTG\/ooze_token_green_22.jpg","category":{"idCategory":1,"categoryName":"Magic Single"},"expansion":"Tokens for MTG","expIcon":258,"number":null,"rarity":"Token"},{"idProduct":295517,"idMetaproduct":224430,"idGame":1,"countReprints":"4","name":{"1":{"idLanguage":1,"languageName":"English","productName":"Etherium Cell Token"},"2":{"idLanguage":2,"languageName":"French","productName":"Etherium Cell Token"},"3":{"idLanguage":3,"languageName":"German","productName":"Etherium Cell Token"},"4":{"idLanguage":4,"languageName":"Spanish","productName":"Etherium Cell Token"},"5":{"idLanguage":5,"languageName":"Italian","productName":"Etherium Cell Token"}},"website":"\/Products\/Singles\/Tokens+for+MTG\/Etherium+Cell+Token","image":".\/img\/cards\/Tokens_for_MTG\/etherium_cell_token.jpg","category":{"idCategory":1,"categoryName":"Magic Single"},"expansion":"Tokens for MTG","expIcon":258,"number":null,"rarity":"Token"},{"idProduct":295518,"idMetaproduct":224429,"idGame":1,"countReprints":"6","name":{"1":{"idLanguage":1,"languageName":"English","productName":"Gremlin Token (Red 2\/2)"},"2":{"idLanguage":2,"languageName":"French","productName":"Gremlin Token (Red 2\/2)"},"3":{"idLanguage":3,"languageName":"German","productName":"Gremlin Token (Red 2\/2)"},"4":{"idLanguage":4,"languageName":"Spanish","productName":"Gremlin Token (Red 2\/2)"},"5":{"idLanguage":5,"languageName":"Italian","productName":"Gremlin Token (Red 2\/2)"}},"website":"\/Products\/Singles\/Tokens+for+MTG\/Gremlin+Token+%28Red+2%2F2%29","image":".\/img\/cards\/Tokens_for_MTG\/gremlin_token_red_22.jpg","category":{"idCategory":1,"categoryName":"Magic Single"},"expansion":"Tokens for MTG","expIcon":258,"number":null,"rarity":"Token"},{"idProduct":293197,"idMetaproduct":223600,"idGame":1,"countReprints":"4","name":{"1":{"idLanguage":1,"languageName":"English","productName":"Assassin Token (Black 1\/1 Deathtouch)"},"2":{"idLanguage":2,"languageName":"French","productName":"Assassin Token (Black 1\/1 Deathtouch)"},"3":{"idLanguage":3,"languageName":"German","productName":"Assassin Token (Black 1\/1 Deathtouch)"},"4":{"idLanguage":4,"languageName":"Spanish","productName":"Assassin Token (Black 1\/1 Deathtouch)"},"5":{"idLanguage":5,"languageName":"Italian","productName":"Assassin Token (Black 1\/1 Deathtouch)"}},"website":"\/Products\/Singles\/Tokens+for+MTG\/Assassin+Token+%28Black+1%2F1+Deathtouch%29","image":".\/img\/cards\/Tokens_for_MTG\/assassin_token_black_11_deathtouch.jpg","category":{"idCategory":1,"categoryName":"Magic Single"},"expansion":"Tokens for MTG","expIcon":258,"number":null,"rarity":"Token"},{"idProduct":295515,"idMetaproduct":224792,"idGame":1,"countReprints":"1","name":{"1":{"idLanguage":1,"languageName":"English","productName":"Assembly-Worker Token (Colorless 2\/2)"},"2":{"idLanguage":2,"languageName":"French","productName":"Assembly-Worker Token (Colorless 2\/2)"},"3":{"idLanguage":3,"languageName":"German","productName":"Assembly-Worker Token (Colorless 2\/2)"},"4":{"idLanguage":4,"languageName":"Spanish","productName":"Assembly-Worker Token (Colorless 2\/2)"},"5":{"idLanguage":5,"languageName":"Italian","productName":"Assembly-Worker Token (Colorless 2\/2)"}},"website":"\/Products\/Singles\/Tokens+for+MTG\/Assembly-Worker+Token+%28Colorless+2%2F2%29","image":".\/img\/cards\/Tokens_for_MTG\/assembly_worker_token_colorless_22.jpg","category":{"idCategory":1,"categoryName":"Magic Single"},"expansion":"Tokens for MTG","expIcon":258,"number":null,"rarity":"Token"},{"idProduct":295516,"idMetaproduct":10559,"idGame":1,"countReprints":"4","name":{"1":{"idLanguage":1,"languageName":"English","productName":"Dragon Token (Red and Green 1\/1)"},"2":{"idLanguage":2,"languageName":"French","productName":"Dragon Token (Red and Green 1\/1)"},"3":{"idLanguage":3,"languageName":"German","productName":"Dragon Token (Red and Green 1\/1)"},"4":{"idLanguage":4,"languageName":"Spanish","productName":"Dragon Token (Red and Green 1\/1)"},"5":{"idLanguage":5,"languageName":"Italian","productName":"Dragon Token (Red and Green 1\/1)"}},"website":"\/Products\/Singles\/Tokens+for+MTG\/Dragon+Token+%28Red+and+Green+1%2F1%29","image":".\/img\/cards\/Tokens_for_MTG\/dragon_token_red_and_green_11.jpg","category":{"idCategory":1,"categoryName":"Magic Single"},"expansion":"Tokens for MTG","expIcon":258,"number":null,"rarity":"Token"},{"idProduct":297849,"idMetaproduct":207818,"idGame":1,"countReprints":"3","name":{"1":{"idLanguage":1,"languageName":"English","productName":"Faerie Token (Black 1\/1) (Version 2)"},"2":{"idLanguage":2,"languageName":"French","productName":"Faerie Token (Black 1\/1) (Version 2)"},"3":{"idLanguage":3,"languageName":"German","productName":"Faerie Token (Black 1\/1) (Version 2)"},"4":{"idLanguage":4,"languageName":"Spanish","productName":"Faerie Token (Black 1\/1) (Version 2)"},"5":{"idLanguage":5,"languageName":"Italian","productName":"Faerie Token (Black 1\/1) (Version 2)"}},"website":"\/Products\/Singles\/Tokens+for+MTG\/Faerie+Token+%28Black+1%2F1%29+%28Version+2%29","image":".\/img\/cards\/Tokens_for_MTG\/faerie_token_black_112.jpg","category":{"idCategory":1,"categoryName":"Magic Single"},"expansion":"Tokens for MTG","expIcon":258,"number":null,"rarity":"Token"},{"idProduct":297854,"idMetaproduct":225541,"idGame":1,"countReprints":"2","name":{"1":{"idLanguage":1,"languageName":"English","productName":"Insect Token (Black 1\/1)"},"2":{"idLanguage":2,"languageName":"French","productName":"Insect Token (Black 1\/1)"},"3":{"idLanguage":3,"languageName":"German","productName":"Insect Token (Black 1\/1)"},"4":{"idLanguage":4,"languageName":"Spanish","productName":"Insect Token (Black 1\/1)"},"5":{"idLanguage":5,"languageName":"Italian","productName":"Insect Token (Black 1\/1)"}},"website":"\/Products\/Singles\/Tokens+for+MTG\/Insect+Token+%28Black+1%2F1%29","image":".\/img\/cards\/Tokens_for_MTG\/insect_token_black_11.jpg","category":{"idCategory":1,"categoryName":"Magic Single"},"expansion":"Tokens for MTG","expIcon":258,"number":null,"rarity":"Token"},{"idProduct":297851,"idMetaproduct":225544,"idGame":1,"countReprints":"3","name":{"1":{"idLanguage":1,"languageName":"English","productName":"Snake Token (Green 1\/1 Deathtouch)"},"2":{"idLanguage":2,"languageName":"French","productName":"Snake Token (Green 1\/1 Deathtouch)"},"3":{"idLanguage":3,"languageName":"German","productName":"Snake Token (Green 1\/1 Deathtouch)"},"4":{"idLanguage":4,"languageName":"Spanish","productName":"Snake Token (Green 1\/1 Deathtouch)"},"5":{"idLanguage":5,"languageName":"Italian","productName":"Snake Token (Green 1\/1 Deathtouch)"}},"website":"\/Products\/Singles\/Tokens+for+MTG\/Snake+Token+%28Green+1%2F1+Deathtouch%29","image":".\/img\/cards\/Tokens_for_MTG\/snake_token_green_11_deathtouch.jpg","category":{"idCategory":1,"categoryName":"Magic Single"},"expansion":"Tokens for MTG","expIcon":258,"number":null,"rarity":"Token"},{"idProduct":297853,"idMetaproduct":221598,"idGame":1,"countReprints":"5","name":{"1":{"idLanguage":1,"languageName":"English","productName":"Angel Token (White 3\/3)"},"2":{"idLanguage":2,"languageName":"French","productName":"Angel Token (White 3\/3)"},"3":{"idLanguage":3,"languageName":"German","productName":"Angel Token (White 3\/3)"},"4":{"idLanguage":4,"languageName":"Spanish","productName":"Angel Token (White 3\/3)"},"5":{"idLanguage":5,"languageName":"Italian","productName":"Angel Token (White 3\/3)"}},"website":"\/Products\/Singles\/Tokens+for+MTG\/Angel+Token+%28White+3%2F3%29","image":".\/img\/cards\/Tokens_for_MTG\/angel_token_white_33.jpg","category":{"idCategory":1,"categoryName":"Magic Single"},"expansion":"Tokens for MTG","expIcon":258,"number":null,"rarity":"Token"},{"idProduct":300271,"idMetaproduct":9107,"idGame":1,"countReprints":"78","name":{"1":{"idLanguage":1,"languageName":"English","productName":"Zombie Token (Black 2\/2) (Version 4)"},"2":{"idLanguage":2,"languageName":"French","productName":"Zombie Token (Black 2\/2) (Version 4)"},"3":{"idLanguage":3,"languageName":"German","productName":"Zombie Token (Black 2\/2) (Version 4)"},"4":{"idLanguage":4,"languageName":"Spanish","productName":"Zombie Token (Black 2\/2) (Version 4)"},"5":{"idLanguage":5,"languageName":"Italian","productName":"Zombie Token (Black 2\/2) (Version 4)"}},"website":"\/Products\/Singles\/Tokens+for+MTG\/Zombie+Token+%28Black+2%2F2%29+%28Version+4%29","image":".\/img\/cards\/Tokens_for_MTG\/zombie_token_black_224.jpg","category":{"idCategory":1,"categoryName":"Magic Single"},"expansion":"Tokens for MTG","expIcon":258,"number":null,"rarity":"Token"},{"idProduct":300272,"idMetaproduct":11008,"idGame":1,"countReprints":"17","name":{"1":{"idLanguage":1,"languageName":"English","productName":"Plant Token (Green 0\/1) (Version 2)"},"2":{"idLanguage":2,"languageName":"French","productName":"Plant Token (Green 0\/1) (Version 2)"},"3":{"idLanguage":3,"languageName":"German","productName":"Plant Token (Green 0\/1) (Version 2)"},"4":{"idLanguage":4,"languageName":"Spanish","productName":"Plant Token (Green 0\/1) (Version 2)"},"5":{"idLanguage":5,"languageName":"Italian","productName":"Plant Token (Green 0\/1) (Version 2)"}},"website":"\/Products\/Singles\/Tokens+for+MTG\/Plant+Token+%28Green+0%2F1%29+%28Version+2%29","image":".\/img\/cards\/Tokens_for_MTG\/plant_token_green_012.jpg","category":{"idCategory":1,"categoryName":"Magic Single"},"expansion":"Tokens for MTG","expIcon":258,"number":null,"rarity":"Token"},{"idProduct":297852,"idMetaproduct":225540,"idGame":1,"countReprints":"8","name":{"1":{"idLanguage":1,"languageName":"English","productName":"Warrior Token (White 1\/1 Vigilance)"},"2":{"idLanguage":2,"languageName":"French","productName":"Warrior Token (White 1\/1 Vigilance)"},"3":{"idLanguage":3,"languageName":"German","productName":"Warrior Token (White 1\/1 Vigilance)"},"4":{"idLanguage":4,"languageName":"Spanish","productName":"Warrior Token (White 1\/1 Vigilance)"},"5":{"idLanguage":5,"languageName":"Italian","productName":"Warrior Token (White 1\/1 Vigilance)"}},"website":"\/Products\/Singles\/Tokens+for+MTG\/Warrior+Token+%28White+1%2F1+Vigilance%29","image":".\/img\/cards\/Tokens_for_MTG\/warrior_token_white_11_vigilance.jpg","category":{"idCategory":1,"categoryName":"Magic Single"},"expansion":"Tokens for MTG","expIcon":258,"number":null,"rarity":"Token"},{"idProduct":300273,"idMetaproduct":226096,"idGame":1,"countReprints":"6","name":{"1":{"idLanguage":1,"languageName":"English","productName":"Insect Token (Blue and Red 1\/1)"},"2":{"idLanguage":2,"languageName":"French","productName":"Insect Token (Blue and Red 1\/1)"},"3":{"idLanguage":3,"languageName":"German","productName":"Insect Token (Blue and Red 1\/1)"},"4":{"idLanguage":4,"languageName":"Spanish","productName":"Insect Token (Blue and Red 1\/1)"},"5":{"idLanguage":5,"languageName":"Italian","productName":"Insect Token (Blue and Red 1\/1)"}},"website":"\/Products\/Singles\/Tokens+for+MTG\/Insect+Token+%28Blue+and+Red+1%2F1%29","image":".\/img\/cards\/Tokens_for_MTG\/insect_token_blue_and_red_11.jpg","category":{"idCategory":1,"categoryName":"Magic Single"},"expansion":"Tokens for MTG","expIcon":258,"number":null,"rarity":"Token"},{"idProduct":300274,"idMetaproduct":226482,"idGame":1,"countReprints":"1","name":{"1":{"idLanguage":1,"languageName":"English","productName":"Horror Token (Black 3\/3)"},"2":{"idLanguage":2,"languageName":"French","productName":"Horror Token (Black 3\/3)"},"3":{"idLanguage":3,"languageName":"German","productName":"Horror Token (Black 3\/3)"},"4":{"idLanguage":4,"languageName":"Spanish","productName":"Horror Token (Black 3\/3)"},"5":{"idLanguage":5,"languageName":"Italian","productName":"Horror Token (Black 3\/3)"}},"website":"\/Products\/Singles\/Tokens+for+MTG\/Horror+Token+%28Black+3%2F3%29","image":".\/img\/cards\/Tokens_for_MTG\/horror_token_black_33.jpg","category":{"idCategory":1,"categoryName":"Magic Single"},"expansion":"Tokens for MTG","expIcon":258,"number":null,"rarity":"Token"},{"idProduct":300275,"idMetaproduct":225539,"idGame":1,"countReprints":"6","name":{"1":{"idLanguage":1,"languageName":"English","productName":"Cat Token (White 1\/1)"},"2":{"idLanguage":2,"languageName":"French","productName":"Cat Token (White 1\/1)"},"3":{"idLanguage":3,"languageName":"German","productName":"Cat Token (White 1\/1)"},"4":{"idLanguage":4,"languageName":"Spanish","productName":"Cat Token (White 1\/1)"},"5":{"idLanguage":5,"languageName":"Italian","productName":"Cat Token (White 1\/1)"}},"website":"\/Products\/Singles\/Tokens+for+MTG\/Cat+Token+%28White+1%2F1%29","image":".\/img\/cards\/Tokens_for_MTG\/cat_token_white_11.jpg","category":{"idCategory":1,"categoryName":"Magic Single"},"expansion":"Tokens for MTG","expIcon":258,"number":null,"rarity":"Token"},{"idProduct":302118,"idMetaproduct":226577,"idGame":1,"countReprints":"3","name":{"1":{"idLanguage":1,"languageName":"English","productName":"Cat Dragon Token (Gold 3\/3)"},"2":{"idLanguage":2,"languageName":"French","productName":"Cat Dragon Token (Gold 3\/3)"},"3":{"idLanguage":3,"languageName":"German","productName":"Cat Dragon Token (Gold 3\/3)"},"4":{"idLanguage":4,"languageName":"Spanish","productName":"Cat Dragon Token (Gold 3\/3)"},"5":{"idLanguage":5,"languageName":"Italian","productName":"Cat Dragon Token (Gold 3\/3)"}},"website":"\/Products\/Singles\/Tokens+for+MTG\/Cat+Dragon+Token+%28Gold+3%2F3%29","image":".\/img\/cards\/Tokens_for_MTG\/cat_dragon_token_gold_33.jpg","category":{"idCategory":1,"categoryName":"Magic Single"},"expansion":"Tokens for MTG","expIcon":258,"number":null,"rarity":"Token"},{"idProduct":302119,"idMetaproduct":226095,"idGame":1,"countReprints":"6","name":{"1":{"idLanguage":1,"languageName":"English","productName":"Horse Token (White 5\/5)"},"2":{"idLanguage":2,"languageName":"French","productName":"Horse Token (White 5\/5)"},"3":{"idLanguage":3,"languageName":"German","productName":"Horse Token (White 5\/5)"},"4":{"idLanguage":4,"languageName":"Spanish","productName":"Horse Token (White 5\/5)"},"5":{"idLanguage":5,"languageName":"Italian","productName":"Horse Token (White 5\/5)"}},"website":"\/Products\/Singles\/Tokens+for+MTG\/Horse+Token+%28White+5%2F5%29","image":".\/img\/cards\/Tokens_for_MTG\/horse_token_white_55.jpg","category":{"idCategory":1,"categoryName":"Magic Single"},"expansion":"Tokens for MTG","expIcon":258,"number":null,"rarity":"Token"},{"idProduct":302120,"idMetaproduct":227069,"idGame":1,"countReprints":"1","name":{"1":{"idLanguage":1,"languageName":"English","productName":"Monkey Token (Red 2\/1)"},"2":{"idLanguage":2,"languageName":"French","productName":"Monkey Token (Red 2\/1)"},"3":{"idLanguage":3,"languageName":"German","productName":"Monkey Token (Red 2\/1)"},"4":{"idLanguage":4,"languageName":"Spanish","productName":"Monkey Token (Red 2\/1)"},"5":{"idLanguage":5,"languageName":"Italian","productName":"Monkey Token (Red 2\/1)"}},"website":"\/Products\/Singles\/Tokens+for+MTG\/Monkey+Token+%28Red+2%2F1%29","image":".\/img\/cards\/Tokens_for_MTG\/monkey_token_red_21.jpg","category":{"idCategory":1,"categoryName":"Magic Single"},"expansion":"Tokens for MTG","expIcon":258,"number":null,"rarity":"Token"},{"idProduct":302121,"idMetaproduct":226883,"idGame":1,"countReprints":"10","name":{"1":{"idLanguage":1,"languageName":"English","productName":"Treasure Token"},"2":{"idLanguage":2,"languageName":"French","productName":"Treasure Token"},"3":{"idLanguage":3,"languageName":"German","productName":"Treasure Token"},"4":{"idLanguage":4,"languageName":"Spanish","productName":"Treasure Token"},"5":{"idLanguage":5,"languageName":"Italian","productName":"Treasure Token"}},"website":"\/Products\/Singles\/Tokens+for+MTG\/Treasure+Token","image":".\/img\/cards\/Tokens_for_MTG\/treasure_token.jpg","category":{"idCategory":1,"categoryName":"Magic Single"},"expansion":"Tokens for MTG","expIcon":258,"number":null,"rarity":"Token"}]}